Workbook

Sheet BASE BI
A1: ticket_id | B1: protocolo | C1: titulo | D1: UsuarioDesignado | E1: segmento_cliente | F1: numplan | G1: idservico | H1: valorservico | I1: produto | J1: cliente_id | K1: Cliente | L1: CNPJ | M1: data_abertura | N1: data_fechamento | O1: substatus | P1: dep_atual | Q1: Canal_Abertura | R1: Tipo_Encerramento | S1: Causa_Raiz | T1: parceiro | U1: ult_OS | V1: os_agrupada | W1: os_concluida_agrupada | X1: ufservico | Y1: cidadeservico | Z1: bdeskprotocol | AA1: aging_ccs | AB1: tempo_total | AC1: tempo_cliente | AD1: tempo_giga | AE1: tempo_suporte_total | AF1: tempo_noc | AG1: tempo_ccs | AH1: tempo_b2b | AI1: tempoccs_campo | AJ1: tempo_escritorio | AK1: tempo_swap | AL1: DataAtivacao | AM1: intervalo_ativacao | AN1: classificacao_ifi | AO1: designator | AP1: nova_regional | AQ1: cluster | AR1: gerente | AS1: sla_ticket | AT1: semana | AU1: ano | AV1: mes | AW1: cluster_calc | AX1: dentro_8h | AY1: outlier_24h | BT1: cluster_calc | BU1: dentro_8h | BV1: outlier_24h
A2: 5738809 | B2: 30122025-78733 | C2: SERVIS ELETRONICA DEFENSE LTDA MA GRUPO SERVIS | INDISPONIBILIDADE | SLS/L2L/218497/771 | D2: Glen Serafim | E2: Corporativo | F2: 768 | G2: 293293 | H2: 471.74 | I2: LINK DE DADOS | J2: 218497 | K2: SERVIS ELETRONICA DEFENSE LTDA MA GRUPO SERVIS | L2: 04.196.136/0003-31 | M2: 46021.768 | N2: 46023.644 | O2: PENDENTE VALIDAÇÃO | P2: CMO - Reparo | R2: Rompimento de Fibra | U2: 165937 | V2: 165937 | W2: 165937 | X2: MA | Y2: SAO LUIS | AA2: Entre 4h e 8h | AB2: 44.966666 | AC2: 39.433333 | AD2: 5.533333 | AE2: 0.25 | AF2: 0 | AG2: 5.283333 | AH2: 5.283333 | AI2: 5.183333 | AJ2: 0.1 | AK2: 0 | AL2: 45191.77 | AM2: 829 | AN2: Maior que 15d pós ativação | AO2: SLS/L2L/218497/768 | AP2: MA, PA, PI E AP | AQ2: C.32 - Maranhão | AR2: Wellington Marcio | AT2: S01 | AU2: 2026 | AV2: 1 | AW2: MA CAP | AX2: 1 | AY2: 0 | BT2: MA CAP | BU2: 1 | BV2: 0
A3: 5739621 | B3: 31122025-59475 | C3: Queda de link primário | D3: Stephanie Aparecida Arthur | E3: Corporativo | F3: 65 | G3: 290179 | H3: 300 | I3: LINK DE DADOS | J3: 13955 | K3: PFM COMERCIAL LTDA - CASA FREITAS | L3: 01.740.627/0001-41 | M3: 46022.355 | N3: 46024.443 | O3: PENDENTE VALIDAÇÃO | P3: CMO - Reparo | Q3: Portal do Cliente | R3: Rompimento de Fibra | U3: 165821 | V3: 165821 | W3: 165821 | X3: PI | Y3: PARNAIBA | AA3: Até 4h | AB3: 50.033335 | AC3: 44.783333 | AD3: 5.250002 | AE3: 2.066668 | AF3: 0 | AG3: 3.183334 | AH3: 3.183334 | AI3: 2.783334 | AJ3: 0.4 | AK3: 0 | AL3: 45026 | AM3: 996 | AN3: Maior que 15d pós ativação | AO3: PNA/L2L/13955/65 | AP3: MA, PA, PI E AP | AQ3: C.31 - Piaui | AR3: Wellington Marcio | AT3: S01 | AU3: 2026 | AV3: 1 | AW3: PI INT | AX3: 1 | AY3: 0 | BT3: PI INT | BU3: 1 | BV3: 0
A4: 5737945 | B4: 30122025-94754 | C4: Atendimento para: SEMOSP - SEDE - SLS-216233-00033 | D4: Stephanie Aparecida Arthur | E4: Público | F4: 33 | G4: 275253 | H4: 740.61 | I4: LINK DE DADOS | J4: 216233 | K4: MUNICIPIO DE SAO LUIS SEMIT | L4: 06.307.102/0001-30 | M4: 46021.585 | N4: 46024.448 | O4: PENDENTE VALIDAÇÃO | P4: CMO - Reparo | Q4: Email | R4: Rompimento de Fibra | U4: 165835 | V4: 165835 | W4: 165835 | X4: MA | Y4: SAO LUIS | Z4: 521037 - Manutenção corretiva || OLT br.ma.sls.chf.gp.02 || SLOT 1; PON 3 a 9 || 67 afetados | AA4: Entre 4h e 8h | AB4: 68.65 | AC4: 41.583333 | AD4: 27.066667 | AE4: 21.816667 | AF4: 21.166667 | AG4: 5.25 | AH4: 26.416667 | AI4: 5.05 | AJ4: 0.2 | AK4: 0 | AL4: 44838 | AM4: 1183 | AN4: Maior que 15d pós ativação | AO4: SLS/L2L/216233/33 | AP4: MA, PA, PI E AP | AQ4: C.32 - Maranhão | AR4: Wellington Marcio | AT4: S01 | AU4: 2026 | AV4: 1 | AW4: MA CAP | AX4: 1 | AY4: 0 | BT4: MA CAP | BU4: 1 | BV4: 0
A5: 5738939 | B5: 30122025-29109 | C5: Atendimento para: UEB ENS FUND NEWTON NEVES - SLS-216233-00288 | D5: Stephanie Aparecida Arthur | E5: Público | F5: 288 | G5: 286441 | H5: 364.96 | I5: LINK DE DADOS | J5: 218787 | K5: MUNICIPIO DE SAO LUIS SEMED | L5: 06.307.102/0002-11 | M5: 46021.85 | N5: 46024.467 | O5: PENDENTE VALIDAÇÃO | P5: CMO - Reparo | Q5: E-Care | R5: Normalizado Sem Intervenção | U5: 165827 | V5: 165827 | X5: MA | Y5: SAO LUIS | AA5: Entre 8h e 12h | AB5: 62.733333 | AC5: 52.983333 | AD5: 9.75 | AE5: 0.233333 | AF5: 0 | AG5: 9.516667 | AH5: 9.516667 | AI5: 9.4 | AJ5: 0.116667 | AK5: 0 | AL5: 44896 | AM5: 1125 | AN5: Maior que 15d pós ativação | AO5: SLS/L2L/218787/288 | AP5: MA, PA, PI E AP | AQ5: C.32 - Maranhão | AR5: Wellington Marcio | AT5: S01 | AU5: 2026 | AV5: 1 | AW5: MA CAP | AX5: 0 | AY5: 0 | BT5: MA CAP | BU5: 0 | BV5: 0
A6: 5734511 | B6: 29122025-60212 | C6: ABERTURA DE CHAMADO/202540973903/GRUPO CASAS BAHIA S A | D6: Stephanie Aparecida Arthur | E6: Operadoras | F6: 122 | G6: 324995 | H6: 650 | I6: LINK DE DADOS | J6: 225215 | K6: VOGEL SOLUCOES EM TELECOMUNICACOES E INFORMATICA S A ALGAR TELECOM | L6: 05.872.814/0013-73 | M6: 46020.661 | N6: 46024.469 | O6: PENDENTE VALIDAÇÃO | P6: CMO - Reparo | Q6: Email | R6: Rompimento de Fibra | U6: 165109 | V6: 164907, 165109 | W6: 165109 | X6: PI | Y6: PICOS | AA6: Entre 4h e 8h | AB6: 91.35 | AC6: 85.616666 | AD6: 5.733334 | AE6: 0.566667 | AF6: 0 | AG6: 5.166667 | AH6: 5.166667 | AI6: 4.816667 | AJ6: 0.35 | AK6: 0 | AL6: 45573.576 | AM6: 447 | AN6: Maior que 15d pós ativação | AO6: PCZ/L2L/225215/122 | AP6: MA, PA, PI E AP | AQ6: C.31 - Piaui | AR6: Wellington Marcio | AT6: S01 | AU6: 2026 | AV6: 1 | AW6: PI INT | AX6: 1 | AY6: 0 | BT6: PI INT | BU6: 1 | BV6: 0
A7: 5720611 | B7: 25122025-57218 | C7: ABERTURA DE CHAMADO - 04.2001 - INC8427715 - MOB TELECOM | D7: Stephanie Aparecida Arthur | E7: Corporativo | F7: 1 | G7: 251091 | H7: 1749.9 | I7: LINK DEDICADO DE INTERNET | J7: 203451 | K7: SICREDI NORTE COOP DE CREDITO UNIDADE DE ATENDIMENTO GENERALISSIMO | L7: 83.315.408/0003-41 | M7: 46016.022 | N7: 46024.474 | O7: PENDENTE VALIDAÇÃO | P7: CMO - Reparo | Q7: Email | R7: Rompimento de Fibra | U7: 165267 | V7: 165267 | W7: 165267 | X7: PA | Y7: BELEM | AA7: Entre 8h e 12h | AB7: 202.81667 | AC7: 175 | AD7: 27.816668 | AE7: 17.033334 | AF7: 0 | AG7: 10.783334 | AH7: 10.783334 | AI7: 10.733334 | AJ7: 0.05 | AK7: 0 | AL7: 44638 | AM7: 1378 | AN7: Maior que 15d pós ativação | AO7: BLM/IPD/203451/1 | AP7: MA, PA, PI E AP | AQ7: C.28 - Norte | AR7: Wellington Marcio | AT7: S01 | AU7: 2026 | AV7: 1 | AW7: PA CAP | AX7: 0 | AY7: 0 | BT7: PA CAP | BU7: 0 | BV7: 0
A8: 5738195 | B8: 30122025-33861 | C8: ARION SERVICOS DE TELECOMUNICACOES LTDA | Indisponibilidade | Contrato 6453266 | D8: Vanessa Alves Ferreira | E8: Provedores | F8: 1 | G8: 335653 | H8: 79.9 | I8: BANDA LARGA WIFI 5 + IP FIXO FS | J8: 201863 | K8: ARION SERVICOS DE TELECOMUNICACOES LTDA ARION SERVICES | L8: 20.059.578/0001-20 | M8: 46021.618 | N8: 46024.477 | O8: PENDENTE VALIDAÇÃO | P8: CMO - Reparo | Q8: Chat | R8: Ajuste de Atenuação | U8: 166051 | V8: 165539, 166051 | W8: 166051 | X8: MA | Y8: PRESIDENTE DUTRA | AA8: Até 4h | AB8: 68.533334 | AC8: 65.066666 | AD8: 3.466668 | AE8: 0.466667 | AF8: 0 | AG8: 3.000001 | AH8: 3.000001 | AI8: 2.716667 | AJ8: 0.283334 | AK8: 0 | AN8: Sem data de ativação | AO8: PDU/FBR/201863/1 | AP8: MA, PA, PI E AP | AQ8: C.32 - Maranhão | AR8: Wellington Marcio | AT8: S01 | AU8: 2026 | AV8: 1 | AW8: MA INT | AX8: 1 | AY8: 0 | BT8: MA INT | BU8: 1 | BV8: 0
A9: 5739173 | B9: 31122025-47557 | C9: RCR LOCACAO LTDA R C R LOCACAO LTDA | INDISPONIBILIDADE | SLS/IPD/226111/1 | D9: Rennan Lima da Penha | E9: Corporativo | F9: 1 | G9: 333399 | H9: 600 | I9: IP CONNECT Metro | J9: 226111 | K9: RCR LOCACAO LTDA R C R LOCACAO LTDA | L9: 01.203.383/0006-72 | M9: 46022.02 | N9: 46024.493 | O9: PENDENTE VALIDAÇÃO | P9: CMO - Reparo | Q9: Chat | R9: Falha Elétrica Cliente | U9: 165983 | V9: 165639, 165983 | W9: 165983 | X9: MA | Y9: SAO LUIS | AA9: Entre 4h e 8h | AB9: 59.233335 | AC9: 51.116667 | AD9: 8.116668 | AE9: 0.166667 | AF9: 0 | AG9: 7.950001 | AH9: 7.950001 | AI9: 7.733334 | AJ9: 0.216667 | AK9: 0 | AL9: 45771.443 | AM9: 250 | AN9: Maior que 15d pós ativação | AO9: SLS/IPD/226111/1 | AP9: MA, PA, PI E AP | AQ9: C.32 - Maranhão | AR9: Wellington Marcio | AT9: S01 | AU9: 2026 | AV9: 1 | AW9: MA CAP | AX9: 1 | AY9: 0 | BT9: MA CAP | BU9: 1 | BV9: 0
A10: 5738689 | B10: 30122025-39784 | C10: Atendimento para: UEB PROF ELPIDIO HERMES DE CARVALHO - POLO | D10: Laura Beatriz de Sibia Santos | E10: Público | F10: 253 | G10: 286349 | H10: 364.96 | I10: LINK DE DADOS | J10: 216233 | K10: MUNICIPIO DE SAO LUIS SEMIT | L10: 06.307.102/0001-30 | M10: 46021.732 | N10: 46024.594 | O10: PENDENTE VALIDAÇÃO | P10: CMO - Reparo | Q10: Email | R10: Ajuste de Atenuação | U10: 165645 | V10: 165645 | W10: 165645 | X10: MA | Y10: SAO LUIS | AA10: Entre 4h e 8h | AB10: 68.616668 | AC10: 62.166667 | AD10: 6.450001 | AE10: 0.483334 | AF10: 0 | AG10: 5.966667 | AH10: 5.966667 | AI10: 5.25 | AJ10: 0.716667 | AK10: 0 | AL10: 44893 | AM10: 1128 | AN10: Maior que 15d pós ativação | AO10: SLS/L2L/218787/253 | AP10: MA, PA, PI E AP | AQ10: C.32 - Maranhão | AR10: Wellington Marcio | AT10: S01 | AU10: 2026 | AV10: 1 | AW10: MA CAP | AX10: 1 | AY10: 0 | BT10: MA CAP | BU10: 1 | BV10: 0
A11: 5734265 | B11: 29122025-37162 | C11: Atendimento para: UEB MARIA AMELIA PROFETA - SLS-216233-00266 | D11: Vinicius da Silva Dos Santos | E11: Público | F11: 266 | G11: 286377 | H11: 364.96 | I11: LINK DE DADOS | J11: 218787 | K11: MUNICIPIO DE SAO LUIS SEMED | L11: 06.307.102/0002-11 | M11: 46020.612 | N11: 46024.692 | O11: PENDENTE VALIDAÇÃO | P11: CMO - Reparo | Q11: E-Care | R11: Configuração | U11: 165975 | V11: 165975, 165989 | W11: 165975 | X11: MA | Y11: SAO LUIS | AA11: Entre 4h e 8h | AB11: 97.716668 | AC11: 85.633333 | AD11: 12.083335 | AE11: 5.000001 | AF11: 0 | AG11: 7.083334 | AH11: 7.083334 | AI11: 7.016667 | AJ11: 0.066667 | AK11: 0 | AL11: 44890 | AM11: 1130 | AN11: Maior que 15d pós ativação | AO11: SLS/L2L/218787/266 | AP11: MA, PA, PI E AP | AQ11: C.32 - Maranhão | AR11: Wellington Marcio | AT11: S01 | AU11: 2026 | AV11: 1 | AW11: MA CAP | AX11: 1 | AY11: 0 | BT11: MA CAP | BU11: 1 | BV11: 0
A12: 5739873 | B12: 31122025-56127 | C12: 3273 SAA AG. AV. GUAJAJARAS LINCK DO NOVO CONTRATO | D12: INGRID DA SILVA CALIXTO SANTANA | E12: Operadoras | F12: 638 | G12: 342937 | H12: 225 | I12: BANDA LARGA WIFI 5 + IP FIXO | J12: 48887 | K12: BRISANET SERVICOS DE TELECOMUNICACOES LTDA BRISANET SERVICOS DE TELECOMUNICACOES LTDA | L12: 04.601.397/0001-28 | M12: 46022.42 | N12: 46024.75 | O12: PENDENTE VALIDAÇÃO | P12: CMO - Reparo | Q12: Portal do Cliente | R12: Rompimento de Fibra | U12: 165985 | V12: 165805, 165985 | W12: 165985 | X12: MA | Y12: SAO LUIS | AA12: Entre 8h e 12h | AB12: 55.816667 | AC12: 47.45 | AD12: 8.366667 | AE12: 0.25 | AF12: 0 | AG12: 8.116667 | AH12: 8.116667 | AI12: 7.516667 | AJ12: 0.6 | AK12: 0 | AL12: 45855 | AM12: 167 | AN12: Maior que 15d pós ativação | AO12: SLS/FBR/48887/638 | AP12: MA, PA, PI E AP | AQ12: C.32 - Maranhão | AR12: Wellington Marcio | AT12: S01 | AU12: 2026 | AV12: 1 | AW12: MA CAP | AX12: 0 | AY12: 0 | BT12: MA CAP | BU12: 0 | BV12: 0
A13: 5741385 | B13: 01012026-28447 | C13: Atendimento para: UEB OLINDA DESTERRO INFANTIL - SLS-216233-00166 | D13: Vinicius da Silva Dos Santos | E13: Público | F13: 166 | G13: 285815 | H13: 364.95 | I13: LINK DE DADOS | J13: 218787 | K13: MUNICIPIO DE SAO LUIS SEMED | L13: 06.307.102/0002-11 | M13: 46023.487 | N13: 46024.775 | O13: PENDENTE VALIDAÇÃO | P13: CMO - Reparo | Q13: Email | R13: Rompimento de Fibra | U13: 165987 | V13: 165987 | W13: 165987 | X13: MA | Y13: SAO LUIS | AA13: Até 4h | AB13: 30.833333 | AC13: 26.866666 | AD13: 3.966667 | AE13: 0.133334 | AF13: 0 | AG13: 3.833333 | AH13: 3.833333 | AI13: 3.733333 | AJ13: 0.1 | AK13: 0 | AL13: 44875 | AM13: 1148 | AN13: Maior que 15d pós ativação | AO13: SLS/L2L/218787/166 | AP13: MA, PA, PI E AP | AQ13: C.32 - Maranhão | AR13: Wellington Marcio | AT13: S01 | AU13: 2026 | AV13: 1 | AW13: MA CAP | AX13: 1 | AY13: 0 | BT13: MA CAP | BU13: 1 | BV13: 0
A14: 5743651 | B14: 03012026-57179 | C14: Indisponivel - São Luis | INOVANET | SLS/L2L/133341/12 | D14: Stephanie Aparecida Arthur | E14: Provedores | F14: 12 | G14: 342751 | H14: 250 | I14: L2L Metro | J14: 133341 | K14: INOVANET EMPREENDIMENTOS LTDA. INOVANET | L14: 21.278.402/0001-22 | M14: 46025.358 | N14: 46025.477 | O14: PENDENTE VALIDAÇÃO | P14: CMO - Reparo | Q14: Chat | R14: Normalizado Sem Intervenção | U14: 166347 | V14: 166347 | X14: MA | Y14: SAO LUIS | AA14: Até 4h | AB14: 2.8 | AC14: 0.05 | AD14: 2.75 | AE14: 0.55 | AF14: 0 | AG14: 2.2 | AH14: 2.2 | AI14: 1.15 | AJ14: 1.05 | AK14: 0 | AL14: 45982.485 | AM14: 42 | AN14: Maior que 15d pós ativação | AO14: SLS/L2L/133341/12 | AP14: MA, PA, PI E AP | AQ14: C.32 - Maranhão | AR14: Wellington Marcio | AT14: S01 | AU14: 2026 | AV14: 1 | AW14: MA CAP | AX14: 1 | AY14: 0 | BT14: MA CAP | BU14: 1 | BV14: 0
A15: 5743253 | B15: 02012026-58558 | C15: SERVIS ELETRONICA DEFENSE | INDISPONIBILIDADE | SLS/L2L/218497/768 | D15: ANA PAULA DA SILVA SANTOS | E15: Corporativo | F15: 768 | G15: 293293 | H15: 471.74 | I15: LINK DE DADOS | J15: 218497 | K15: SERVIS ELETRONICA DEFENSE LTDA MA GRUPO SERVIS | L15: 04.196.136/0003-31 | M15: 46024.886 | N15: 46025.557 | O15: PENDENTE VALIDAÇÃO | P15: CMO - Reparo | Q15: Chat | R15: Rompimento de Fibra | U15: 166257 | V15: 166257 | W15: 166257 | X15: MA | Y15: SAO LUIS | AA15: Entre 4h e 8h | AB15: 16.033334 | AC15: 11.266667 | AD15: 4.766667 | AE15: 0.05 | AF15: 0 | AG15: 4.716667 | AH15: 4.716667 | AI15: 3.766667 | AJ15: 0.95 | AK15: 0 | AL15: 45191.77 | AM15: 833 | AN15: Maior que 15d pós ativação | AO15: SLS/L2L/218497/768 | AP15: MA, PA, PI E AP | AQ15: C.32 - Maranhão | AR15: Wellington Marcio | AT15: S01 | AU15: 2026 | AV15: 1 | AW15: MA CAP | AX15: 1 | AY15: 0 | BT15: MA CAP | BU15: 1 | BV15: 0
A16: 5743129 | B16: 02012026-98049 | C16: FBR DIGITAL SA FBR DIGITAL | INDISPONIBILIDADE | ZED/FBR/74371/9 | D16: INGRID DA SILVA CALIXTO SANTANA | E16: Corporativo | F16: 9 | G16: 335547 | H16: 199.8 | I16: BANDA LARGA WIFI 5 + IP FIXO | J16: 74371 | K16: FBR DIGITAL SA FBR DIGITAL | L16: 12.868.281/0001-88 | M16: 46024.787 | N16: 46026.387 | O16: PENDENTE VALIDAÇÃO | P16: CMO - Reparo | Q16: Chat | R16: Normalizado Sem Intervenção | U16: 166275 | V16: 166275, 166327 | W16: 166275 | X16: MA | Y16: ZE DOCA | AA16: Até 4h | AB16: 38.333333 | AC16: 34.933334 | AD16: 3.399999 | AE16: 0.566666 | AF16: 0 | AG16: 2.833333 | AH16: 2.833333 | AI16: 1.45 | AJ16: 1.383333 | AK16: 0 | AN16: Sem data de ativação | AO16: ZED/FBR/74371/9 | AP16: MA, PA, PI E AP | AQ16: C.32 - Maranhão | AR16: Wellington Marcio | AT16: S01 | AU16: 2026 | AV16: 1 | AW16: MA INT | AX16: 1 | AY16: 0 | BT16: MA INT | BU16: 1 | BV16: 0
A17: 5743925 | B17: 03012026-88271 | C17: JF COMERCIO E SERVICOS OPTICOS LTDA | INDISPONIBIDADE| SLS/FBR/229099/23 | D17: Joao Victor Santos Medeiros | E17: Corporativo | F17: 23 | G17: 58375 | H17: 315 | I17: SUPER LIGEIRO CORPORATIVO | J17: 229099 | K17: JF COMERCIO E SERVICOS OPTICOS LTDA | L17: 47.812.518/0001-93 | M17: 46025.516 | N17: 46027.378 | O17: PENDENTE VALIDAÇÃO | P17: CMO - Reparo | Q17: Chat | R17: Normalizado Sem Intervenção | U17: 166395 | V17: 166395 | X17: MA | Y17: SAO LUIS | AA17: Até 4h | AB17: 44.616667 | AC17: 39.733334 | AD17: 4.883333 | AE17: 1.483333 | AF17: 0 | AG17: 3.4 | AH17: 3.4 | AI17: 2.716667 | AJ17: 0.683333 | AK17: 0 | AL17: 42991 | AM17: 3034 | AN17: Maior que 15d pós ativação | AO17: SLS/FBR/229099/23 | AP17: MA, PA, PI E AP | AQ17: C.32 - Maranhão | AR17: Wellington Marcio | AT17: S02 | AU17: 2026 | AV17: 1 | AW17: MA CAP | AX17: 1 | AY17: 0 | BT17: MA CAP | BU17: 1 | BV17: 0
A18: 5742833 | B18: 02012026-79262 | C18: Perda de Conexão | D18: Stephanie Aparecida Arthur | E18: Corporativo | F18: 1 | G18: 344359 | H18: 450 | I18: IP CONNECT GPON | J18: 228519 | K18: MARANHAO MOTOSSERRAS E MAQUINAS LTDA MARANHAO MOTOSSERRAS E MAQUINAS | L18: 01.501.831/0001-00 | M18: 46024.626 | N18: 46027.425 | O18: PENDENTE VALIDAÇÃO | P18: CMO - Reparo | Q18: Portal do Cliente | R18: Rompimento de Fibra | U18: 166301 | V18: 166205, 166229, 166301 | W18: 166301 | X18: MA | Y18: SAO LUIS | AA18: Entre 4h e 8h | AB18: 67.100002 | AC18: 61.583334 | AD18: 5.516668 | AE18: 0.133334 | AF18: 0 | AG18: 5.383334 | AH18: 5.383334 | AI18: 5.133334 | AJ18: 0.25 | AK18: 0 | AL18: 45917 | AM18: 107 | AN18: Maior que 15d pós ativação | AO18: SLS/IPD/228519/1 | AP18: MA, PA, PI E AP | AQ18: C.32 - Maranhão | AR18: Wellington Marcio | AT18: S02 | AU18: 2026 | AV18: 1 | AW18: MA CAP | AX18: 1 | AY18: 0 | BT18: MA CAP | BU18: 1 | BV18: 0
A19: 5742785 | B19: 02012026-17277 | C19: Atendimento para: POSTO SALVA VIDA - PONTA DA AREIA - VLAN-4012 SLS-216233-00422 | D19: Stephanie Aparecida Arthur | E19: Público | F19: 422 | G19: 289265 | H19: 740.61 | I19: LINK DE DADOS | J19: 216233 | K19: MUNICIPIO DE SAO LUIS SEMIT | L19: 06.307.102/0001-30 | M19: 46024.612 | N19: 46027.427 | O19: PENDENTE VALIDAÇÃO | P19: CMO - Reparo | Q19: Email | R19: Ajuste de Atenuação | U19: 166189 | V19: 166189 | W19: 166189 | X19: MA | Y19: SAO LUIS | AA19: Entre 4h e 8h | AB19: 67.516667 | AC19: 62.7 | AD19: 4.816667 | AE19: 0.05 | AF19: 0 | AG19: 4.766667 | AH19: 4.766667 | AI19: 4.766667 | AJ19: 0 | AK19: 0 | AL19: 45021 | AM19: 1003 | AN19: Maior que 15d pós ativação | AO19: SLS/L2L/216233/422 | AP19: MA, PA, PI E AP | AQ19: C.32 - Maranhão | AR19: Wellington Marcio | AT19: S02 | AU19: 2026 | AV19: 1 | AW19: MA CAP | AX19: 1 | AY19: 0 | BT19: MA CAP | BU19: 1 | BV19: 0
A20: 5743875 | B20: 03012026-86894 | C20: CAIXA ECONOMICA FEDERAL | INDISPONIBILIDADE | SLS/L2L/204393/731 | D20: Stephanie Aparecida Arthur | E20: Público | F20: 731 | G20: 244513 | H20: 763.82 | I20: LINK DE DADOS | J20: 204393 | K20: CAIXA ECONOMICA FEDERAL CAIXA ECONOMICA FEDERAL CEF MATRIZ | L20: 00.360.305/0001-04 | M20: 46025.492 | N20: 46027.434 | O20: PENDENTE VALIDAÇÃO | P20: CMO - Reparo | Q20: Chat | R20: Normalizado Sem Intervenção | U20: 166397 | V20: 166397 | X20: MA | Y20: SAO LUIS | AA20: Até 4h | AB20: 46.566667 | AC20: 43.4 | AD20: 3.166667 | AE20: 2.266667 | AF20: 0 | AG20: 0.9 | AH20: 0.9 | AI20: 0.4 | AJ20: 0.5 | AK20: 0 | AL20: 44420 | AM20: 1605 | AN20: Maior que 15d pós ativação | AO20: SLS/L2L/204393/731 | AP20: MA, PA, PI E AP | AQ20: C.32 - Maranhão | AR20: Wellington Marcio | AT20: S02 | AU20: 2026 | AV20: 1 | AW20: MA CAP | AX20: 1 | AY20: 0 | BT20: MA CAP | BU20: 1 | BV20: 0
A21: 5745737 | B21: 05012026-20487 | C21: DISTRIBUIDORA CUMMINS DIESEL DO NORDESTE LTDA | INDISPONIBILIDADE | TSA/IPD/226465/1 | D21: ANA PAULA DA SILVA SANTOS | E21: Corporativo | F21: 1 | G21: 333769 | H21: 330 | I21: IP CONNECT GPON | J21: 226465 | K21: DISTRIBUIDORA CUMMINS DIESEL DO NORDESTE LTDA | L21: 07.301.609/0012-00 | M21: 46027.354 | N21: 46027.445 | O21: PENDENTE VALIDAÇÃO | P21: CMO - Reparo | Q21: Chat | R21: Rompimento de Fibra | U21: 166659 | V21: 166659 | W21: 166659 | X21: PI | Y21: TERESINA | AA21: Até 4h | AB21: 2.133333 | AC21: 0.2 | AD21: 1.933333 | AE21: 0.083333 | AF21: 0 | AG21: 1.85 | AH21: 1.85 | AI21: 1.833333 | AJ21: 0.016667 | AK21: 0 | AL21: 45750.556 | AM21: 276 | AN21: Maior que 15d pós ativação | AO21: TSA/IPD/226465/1 | AP21: MA, PA, PI E AP | AQ21: C.31 - Piaui | AR21: Wellington Marcio | AT21: S02 | AU21: 2026 | AV21: 1 | AW21: PI CAP | AX21: 1 | AY21: 0 | BT21: PI CAP | BU21: 1 | BV21: 0
A22: 5743249 | B22: 02012026-62698 | C22: ALERTA: CLI | IFMA.SIS.SANTA-INES - FALHA | D22: Vanessa Alves Ferreira | E22: Público | F22: 1 | G22: 250779 | H22: 2000 | I22: LINK DEDICADO DE INTERNET | J22: 203401 | K22: INSTITUTO FEDERAL DE EDUCACAO CIENCIA E TECNOLOGIA DO MARANHAO INSTITUTO FEDERAL DO MARANHAO CAMPUS SANTA INES | L22: 10.735.145/0009-41 | M22: 46024.882 | N22: 46027.448 | O22: PENDENTE VALIDAÇÃO | P22: CMO - Reparo | Q22: Email | R22: Normalizado Sem Intervenção | T22: ATEX NET TELECOMUNICAÇÕES LTDA | U22: 166285 | V22: 166285 | W22: 166285 | X22: MA | Y22: SANTA INES | AA22: Até 4h | AB22: 61.466668 | AC22: 52.933334 | AD22: 8.533334 | AE22: 4.55 | AF22: 0 | AG22: 3.983334 | AH22: 3.983334 | AI22: 2.283334 | AJ22: 1.7 | AK22: 0 | AL22: 44650 | AM22: 1374 | AN22: Maior que 15d pós ativação | AO22: SIS/IPD/203401/1 | AP22: MA, PA, PI E AP | AQ22: C.32 - Maranhão | AR22: Wellington Marcio | AT22: S02 | AU22: 2026 | AV22: 1 | AW22: MA INT | AX22: 1 | AY22: 0 | BT22: MA INT | BU22: 1 | BV22: 0
A23: 5743653 | B23: 03012026-46031 | C23: Indisponivel - São Luis | INOVANET | SLS/L2L/133341/17 | D23: Stephanie Aparecida Arthur | E23: Provedores | F23: 17 | G23: 342777 | H23: 250 | I23: L2L Metro | J23: 133341 | K23: INOVANET EMPREENDIMENTOS LTDA. INOVANET | L23: 21.278.402/0001-22 | M23: 46025.359 | N23: 46027.472 | O23: PENDENTE VALIDAÇÃO | P23: CMO - Reparo | Q23: Chat | R23: Falha Elétrica Cliente | U23: 166525 | V23: 166353, 166525 | W23: 166525 | X23: MA | Y23: SAO LUIS | AA23: Entre 8h e 12h | AB23: 50.599998 | AC23: 40.899999 | AD23: 9.699999 | AE23: 0.466666 | AF23: 0 | AG23: 9.233333 | AH23: 9.233333 | AI23: 7.95 | AJ23: 1.283333 | AK23: 0 | AL23: 45996.736 | AM23: 28 | AN23: Maior que 15d pós ativação | AO23: SLS/L2L/133341/17 | AP23: MA, PA, PI E AP | AQ23: C.32 - Maranhão | AR23: Wellington Marcio | AT23: S02 | AU23: 2026 | AV23: 1 | AW23: MA CAP | AX23: 0 | AY23: 0 | BT23: MA CAP | BU23: 0 | BV23: 0
A24: 5743677 | B24: 03012026-95775 | C24: ALERTA: CLI | UFPI.FLO.FLORIANO.IPD.209013.3 - FALHA | D24: Vinicius da Silva Dos Santos | E24: Público | F24: 3 | G24: 280783 | H24: 6464.5 | I24: INTERNET DEDICADA - SCM(Wire) | J24: 209013 | K24: Universidade Federal do Piaui | L24: 06.517.387/0001-34 | M24: 46025.376 | N24: 46027.526 | O24: PENDENTE VALIDAÇÃO | P24: CMO - Reparo | Q24: Email | R24: Normalizado Sem Intervenção | U24: 166553 | V24: 166331, 166553 | X24: PI | Y24: FLORIANO | AA24: Entre 4h e 8h | AB24: 51.5 | AC24: 46.866666 | AD24: 4.633334 | AE24: 0.283333 | AF24: 0 | AG24: 4.350001 | AH24: 4.350001 | AI24: 1.316667 | AJ24: 3.033334 | AK24: 0 | AL24: 44834 | AM24: 1191 | AN24: Maior que 15d pós ativação | AO24: FLO/IPD/209013/3 | AP24: MA, PA, PI E AP | AQ24: C.31 - Piaui | AR24: Wellington Marcio | AT24: S02 | AU24: 2026 | AV24: 1 | AW24: PI INT | AX24: 1 | AY24: 0 | BT24: PI INT | BU24: 1 | BV24: 0
A25: 5744179 | B25: 03012026-45902 | C25: SECOPI SERVICOS COMERCIAS DO PIAUI | INDISPONIBILIDADE | TSA/L2L/41553/791 | D25: Laura Beatriz de Sibia Santos | E25: Corporativo | F25: 791 | G25: 287085 | H25: 209.66 | I25: LINK DE DADOS | J25: 41553 | K25: SECOPI SERVICOS COMERCIAS DO PIAUI LTDA GRUPO SERVIS | L25: 03.582.594/0001-84 | M25: 46025.678 | N25: 46027.529 | O25: PENDENTE VALIDAÇÃO | P25: CMO - Reparo | Q25: Chat | R25: Ajuste de Atenuação | U25: 166441 | V25: 166411, 166441 | W25: 166441 | X25: PI | Y25: TERESINA | AA25: Entre 4h e 8h | AB25: 44.333334 | AC25: 36.716667 | AD25: 7.616667 | AE25: 0.133334 | AF25: 0 | AG25: 7.483333 | AH25: 7.483333 | AI25: 7.45 | AJ25: 0.033333 | AK25: 0 | AL25: 45058 | AM25: 967 | AN25: Maior que 15d pós ativação | AO25: TSA/L2L/41553/791 | AP25: MA, PA, PI E AP | AQ25: C.31 - Piaui | AR25: Wellington Marcio | AT25: S02 | AU25: 2026 | AV25: 1 | AW25: PI CAP | AX25: 1 | AY25: 0 | BT25: PI CAP | BU25: 1 | BV25: 0
A26: 5743831 | B26: 03012026-48961 | C26: sem conexão | D26: Julia Ferreira Costa Silva | E26: Corporativo | F26: 11 | G26: 295427 | H26: 200 | I26: LINK DE DADOS | J26: 218297 | K26: J FEITOSA SILVA FILHO LOJAS SANTA MARIA | L26: 05.017.606/0001-53 | M26: 46025.472 | N26: 46027.653 | O26: PENDENTE VALIDAÇÃO | P26: CMO - Reparo | Q26: Portal do Cliente | R26: Rompimento de Fibra | U26: 166529 | V26: 166367, 166529 | W26: 166529 | X26: MA | Y26: SAO LUIS | AA26: Entre 4h e 8h | AB26: 52.299998 | AC26: 44.233333 | AD26: 8.066665 | AE26: 0.233333 | AF26: 0 | AG26: 7.833332 | AH26: 7.833332 | AI26: 6.499999 | AJ26: 1.333333 | AK26: 0 | AL26: 45293.488 | AM26: 731 | AN26: Maior que 15d pós ativação | AO26: SLS/L2L/218297/11 | AP26: MA, PA, PI E AP | AQ26: C.32 - Maranhão | AR26: Wellington Marcio | AT26: S02 | AU26: 2026 | AV26: 1 | AW26: MA CAP | AX26: 1 | AY26: 0 | BT26: MA CAP | BU26: 1 | BV26: 0
A27: 5746425 | B27: 05012026-37950 | C27: IBL BANDA LARGA INTERNET | INDISPONIBILIDADE | ITZ-L2L-MOJ-F-#102506 | D27: HOANNA MARIA DA SILVA ALBUQUERQUE | E27: Provedores | F27: 4 | G27: 270677 | H27: 51250 | I27: TRANSPORTE LAN TO LAN(Wire) | J27: 210723 | K27: IBL BANDA LARGA INTERNET INFORMATICA LTDA I B L | L27: 08.854.699/0001-69 | M27: 46027.478 | N27: 46027.753 | O27: AGUARDANDO LIBERAÇÃO DE ACESSO | P27: CMO - Reparo | Q27: Chat | R27: Normalizado Sem Intervenção | U27: 166933 | V27: 166933 | X27: MA | Y27: IMPERATRIZ | AA27: Até 4h | AB27: 6.55 | AC27: 2.566667 | AD27: 3.983333 | AE27: 0.383333 | AF27: 0 | AG27: 3.6 | AH27: 3.6 | AI27: 3.45 | AJ27: 0.15 | AK27: 0 | AL27: 36526 | AM27: 9501 | AN27: Maior que 15d pós ativação | AO27: FLA/L2L/210723/4 | AP27: MA, PA, PI E AP | AQ27: C.32 - Maranhão | AR27: Wellington Marcio | AT27: S02 | AU27: 2026 | AV27: 1 | AW27: MA INT | AX27: 1 | AY27: 0 | BT27: MA INT | BU27: 1 | BV27: 0
A28: 5747347 | B28: 05012026-89943 | C28: IAP COSMETICOS LTDA| SLS/IPD/56175/5| INDISPONIBILIDADE | D28: INGRID DA SILVA CALIXTO SANTANA | E28: Corporativo | F28: 5 | G28: 53503 | H28: 402.42 | I28: LINK DEDICADO DE INTERNET | J28: 56175 | K28: IAP COSMETICOS LTDA | L28: 05.346.644/0031-75 | M28: 46027.668 | N28: 46027.775 | O28: AGUARDANDO DISPONIBILIDADE TECNICA | P28: CMO - Reparo | Q28: Chat | R28: Normalizado Sem Intervenção | U28: 167141 | V28: 167141 | X28: MA | Y28: SAO LUIS | AA28: Até 4h | AB28: 2.533333 | AC28: 0 | AD28: 2.533333 | AE28: 0.5 | AF28: 0 | AG28: 2.033333 | AI28: 1.75 | AJ28: 0.283333 | AK28: 0 | AL28: 42625.625 | AM28: 3402 | AN28: Maior que 15d pós ativação | AO28: SLS/IPD/56175/5 | AP28: MA, PA, PI E AP | AQ28: C.32 - Maranhão | AR28: Wellington Marcio | AT28: S02 | AU28: 2026 | AV28: 1 | AW28: MA CAP | AX28: 1 | AY28: 0 | BT28: MA CAP | BU28: 1 | BV28: 0
A29: 5740853 | B29: 01012026-39828 | C29: Indisponibilidade de LantoLan | FILIAL 06 - L2L - GIGA | Grupo TUPAN | D29: ANDRESSA CHRISTINE MOREIRA DA SILVA | E29: Corporativo | F29: 3 | G29: 292843 | H29: 995.89 | I29: LINK DE DADOS | J29: 21243 | K29: DISTRIBUIDORA ADAUTO CARVALHO LTDA | L29: 08.072.649/0002-00 | M29: 46023.028 | N29: 46027.807 | O29: PENDENTE VALIDAÇÃO | P29: CMO - Reparo | Q29: Email | R29: Rompimento de Fibra | U29: 166939 | V29: 165909, 166333, 166939 | W29: 166939 | X29: MA | Y29: TIMON | AA29: Entre 8h e 12h | AB29: 114.56667 | AC29: 101.56667 | AD29: 13 | AE29: 1.95 | AF29: 0 | AG29: 11.05 | AH29: 11.05 | AI29: 8.883333 | AJ29: 2.166667 | AK29: 0 | AL29: 45281.609 | AM29: 741 | AN29: Maior que 15d pós ativação | AO29: TMN/L2L/21243/3 | AP29: MA, PA, PI E AP | AQ29: C.32 - Maranhão | AR29: Wellington Marcio | AT29: S02 | AU29: 2026 | AV29: 1 | AW29: MA INT | AX29: 0 | AY29: 0 | BT29: MA INT | BU29: 0 | BV29: 0
A30: 5740031 | B30: 31122025-28032 | C30: ABERTURA DE REPARO ( LOJA 1132 - LINK MOB INOPERANTE ) | D30: ANDRESSA CHRISTINE MOREIRA DA SILVA | E30: Corporativo | F30: 546 | G30: 65165 | H30: 304.88 | I30: LINK DEDICADO DE INTERNET | J30: 6421 | K30: EMPREENDIMENTOS PAGUE MENOS SA PAGUE MENOS | L30: 06.626.253/0001-51 | M30: 46022.487 | N30: 46027.817 | O30: PENDENTE VALIDAÇÃO | P30: CMO - Reparo | Q30: Email | R30: Rompimento de Fibra | U30: 166521 | V30: 165837, 165979, 166521 | W30: 166521 | X30: MA | Y30: SAO LUIS | AA30: Maior que 24h | AB30: 127.73333 | AC30: 74.95 | AD30: 52.783333 | AE30: 0.316666 | AF30: 0 | AG30: 52.466667 | AH30: 52.466667 | AI30: 42.016667 | AJ30: 10.45 | AK30: 0 | AL30: 43088 | AM30: 2934 | AN30: Maior que 15d pós ativação | AO30: SLS/IPD/6421/546 | AP30: MA, PA, PI E AP | AQ30: C.32 - Maranhão | AR30: Wellington Marcio | AT30: S02 | AU30: 2026 | AV30: 1 | AW30: MA CAP | AX30: 0 | AY30: 1 | BT30: MA CAP | BU30: 0 | BV30: 1
A31: 5740003 | B31: 31122025-97825 | C31: IAP COSMETICOS LTDA || Indisponibilidade || SLS/IPD/56169/7 | D31: ANDRESSA CHRISTINE MOREIRA DA SILVA | E31: Corporativo | F31: 7 | G31: 53523 | H31: 371.35 | I31: LINK DEDICADO DE INTERNET | J31: 56169 | K31: IAP COSMETICOS LTDA | L31: 05.346.644/0033-37 | M31: 46022.472 | N31: 46027.822 | O31: PENDENTE VALIDAÇÃO | P31: CMO - Reparo | Q31: Chat | R31: Rompimento de Fibra | U31: 166523 | V31: 165823, 165981, 166523, 166965 | W31: 166523 | X31: MA | Y31: SAO LUIS | AA31: Maior que 24h | AB31: 128.23333 | AC31: 85.066666 | AD31: 43.166668 | AE31: 0.116667 | AF31: 0 | AG31: 43.050001 | AH31: 43.050001 | AI31: 43.033334 | AJ31: 0.016667 | AK31: 0 | AL31: 42843 | AM31: 3179 | AN31: Maior que 15d pós ativação | AO31: SLS/IPD/56169/7 | AP31: MA, PA, PI E AP | AQ31: C.32 - Maranhão | AR31: Wellington Marcio | AT31: S02 | AU31: 2026 | AV31: 1 | AW31: MA CAP | AX31: 0 | AY31: 1 | BT31: MA CAP | BU31: 0 | BV31: 1
A32: 5744841 | B32: 04012026-60706 | C32: MOBWIRE - ALERTA: CLI | PADRE CICERO MATRIZ MONTESE | D32: Vinicius da Silva Dos Santos | E32: Corporativo | F32: 16 | G32: 298395 | H32: 640 | I32: LINK DE DADOS | J32: 202197 | K32: AUTO PECAS PADRE CICERO LTDA 0 | L32: 07.965.809/0001-05 | M32: 46026.473 | N32: 46028.359 | O32: PENDENTE VALIDAÇÃO | P32: CMO - Reparo | Q32: Email | R32: Ajuste de Atenuação | U32: 166539 | V32: 166477, 166539 | W32: 166477 | X32: MA | Y32: SAO LUIS | AA32: Até 4h | AB32: 45.216667 | AC32: 40.966667 | AD32: 4.25 | AE32: 0.516667 | AF32: 0 | AG32: 3.733333 | AH32: 3.733333 | AI32: 3.666667 | AJ32: 0.066666 | AK32: 0 | AL32: 45302 | AM32: 724 | AN32: Maior que 15d pós ativação | AO32: SLS/L2L/202197/16 | AP32: MA, PA, PI E AP | AQ32: C.32 - Maranhão | AR32: Wellington Marcio | AT32: S02 | AU32: 2026 | AV32: 1 | AW32: MA CAP | AX32: 1 | AY32: 0 | BT32: MA CAP | BU32: 1 | BV32: 0
A33: 5745147 | B33: 04012026-34348 | C33: Atendimento para: CAPS I RH - VLAN-3670 SLS-216233-00114 | D33: Vinicius da Silva Dos Santos | E33: Público | F33: 114 | G33: 285557 | H33: 368.16 | I33: LINK DE DADOS | J33: 218791 | K33: FUNDO MUNICIPAL DE SAUDE DE SAO LUIS MARANHAO | L33: 13.816.886/0001-98 | M33: 46026.806 | N33: 46028.362 | O33: PENDENTE VALIDAÇÃO | P33: CMO - Reparo | Q33: Email | R33: Rompimento de Fibra | U33: 166533 | V33: 166499, 166533 | W33: 166499 | X33: MA | Y33: SAO LUIS | AA33: Até 4h | AB33: 37.266666 | AC33: 33.1 | AD33: 4.166666 | AE33: 0.316666 | AF33: 0 | AG33: 3.85 | AH33: 3.85 | AI33: 3.65 | AJ33: 0.2 | AK33: 0 | AL33: 44874.648 | AM33: 1152 | AN33: Maior que 15d pós ativação | AO33: SLS/L2L/218791/114 | AP33: MA, PA, PI E AP | AQ33: C.32 - Maranhão | AR33: Wellington Marcio | AT33: S02 | AU33: 2026 | AV33: 1 | AW33: MA CAP | AX33: 1 | AY33: 0 | BT33: MA CAP | BU33: 1 | BV33: 0
A34: 5744145 | B34: 03012026-94698 | C34: Atendimento para: POSTO SALVA VIDA - PONTA DA AREIA - VLAN-4012 SLS-216233-00422 | D34: Vinicius da Silva Dos Santos | E34: Público | F34: 422 | G34: 289265 | H34: 740.61 | I34: LINK DE DADOS | J34: 216233 | K34: MUNICIPIO DE SAO LUIS SEMIT | L34: 06.307.102/0001-30 | M34: 46025.667 | N34: 46028.364 | O34: PENDENTE VALIDAÇÃO | P34: CMO - Reparo | Q34: Email | R34: Rompimento de Fibra | U34: 166531 | V34: 166531 | W34: 166531 | X34: MA | Y34: SAO LUIS | AA34: Entre 8h e 12h | AB34: 64.65 | AC34: 54 | AD34: 10.65 | AE34: 0.783333 | AF34: 0 | AG34: 9.866667 | AH34: 9.866667 | AI34: 9.283334 | AJ34: 0.583333 | AK34: 0 | AL34: 45021 | AM34: 1004 | AN34: Maior que 15d pós ativação | AO34: SLS/L2L/216233/422 | AP34: MA, PA, PI E AP | AQ34: C.32 - Maranhão | AR34: Wellington Marcio | AT34: S02 | AU34: 2026 | AV34: 1 | AW34: MA CAP | AX34: 0 | AY34: 0 | BT34: MA CAP | BU34: 0 | BV34: 0
A35: 5743523 | B35: 03012026-38870 | C35: Atendimento para: UEB ENS FUND URUATI - SLS-216233-00375 | D35: Vinicius da Silva Dos Santos | E35: Público | F35: 375 | G35: 286793 | H35: 364.96 | I35: LINK DE DADOS | J35: 218787 | K35: MUNICIPIO DE SAO LUIS SEMED | L35: 06.307.102/0002-11 | M35: 46025.216 | N35: 46028.365 | O35: PENDENTE VALIDAÇÃO | P35: CMO - Reparo | Q35: Email | R35: Ajuste de Atenuação | U35: 166551 | V35: 166289, 166551 | W35: 166551 | X35: MA | Y35: SAO LUIS | AA35: Entre 4h e 8h | AB35: 75.516666 | AC35: 70.583333 | AD35: 4.933333 | AE35: 0.483333 | AF35: 0 | AG35: 4.45 | AH35: 4.45 | AI35: 3.066667 | AJ35: 1.383333 | AK35: 0 | AL35: 44939 | AM35: 1086 | AN35: Maior que 15d pós ativação | AO35: SLS/L2L/218787/375 | AP35: MA, PA, PI E AP | AQ35: C.32 - Maranhão | AR35: Wellington Marcio | AT35: S02 | AU35: 2026 | AV35: 1 | AW35: MA CAP | AX35: 1 | AY35: 0 | BT35: MA CAP | BU35: 1 | BV35: 0
A36: 5745245 | B36: 04012026-75805 | C36: Atendimento para: UEB PROTECAO DE JESUS e UEB ENS FUND PROTECAO DE JESUS - SLS-216233-00393 | D36: Vinicius da Silva Dos Santos | E36: Público | F36: 393 | G36: 286891 | H36: 364.96 | I36: LINK DE DADOS | J36: 218787 | K36: MUNICIPIO DE SAO LUIS SEMED | L36: 06.307.102/0002-11 | M36: 46026.931 | N36: 46028.366 | O36: PENDENTE VALIDAÇÃO | P36: CMO - Reparo | Q36: Email | R36: Rompimento de Fibra | U36: 166513 | V36: 166513, 166535 | W36: 166513 | X36: MA | Y36: SAO LUIS | AA36: Entre 4h e 8h | AB36: 34.383334 | AC36: 26.416667 | AD36: 7.966667 | AE36: 0.2 | AF36: 0 | AG36: 7.766667 | AH36: 7.766667 | AI36: 7.4 | AJ36: 0.366667 | AK36: 0 | AL36: 44974 | AM36: 1052 | AN36: Maior que 15d pós ativação | AO36: SLS/L2L/218787/393 | AP36: MA, PA, PI E AP | AQ36: C.32 - Maranhão | AR36: Wellington Marcio | AT36: S02 | AU36: 2026 | AV36: 1 | AW36: MA CAP | AX36: 1 | AY36: 0 | BT36: MA CAP | BU36: 1 | BV36: 0
A37: 5747277 | B37: 05012026-44302 | C37: LINK INOPERANTE - LOJA 20 - GUAXENDUBA | D37: Vinicius da Silva Dos Santos | E37: Corporativo | F37: 16 | G37: 50431 | H37: 300 | I37: LINK DE DADOS | J37: 13955 | K37: PFM COMERCIAL LTDA - CASA FREITAS | L37: 01.740.627/0001-41 | M37: 46027.656 | N37: 46028.395 | O37: PENDENTE VALIDAÇÃO | P37: CMO - Reparo | Q37: Portal do Cliente | R37: Normalizado Sem Intervenção | U37: 167221 | V37: 167091, 167173, 167221, 167437 | W37: 167173 | X37: MA | Y37: SAO LUIS | AA37: Até 4h | AB37: 17.666666 | AC37: 14.299999 | AD37: 3.366667 | AE37: 0.216667 | AF37: 0 | AG37: 3.15 | AH37: 3.15 | AI37: 3 | AJ37: 0.15 | AK37: 0 | AL37: 42332 | AM37: 3695 | AN37: Maior que 15d pós ativação | AO37: SLS/L2L/13955/16 | AP37: MA, PA, PI E AP | AQ37: C.32 - Maranhão | AR37: Wellington Marcio | AT37: S02 | AU37: 2026 | AV37: 1 | AW37: MA CAP | AX37: 1 | AY37: 0 | BT37: MA CAP | BU37: 1 | BV37: 0
A38: 5746191 | B38: 05012026-34268 | C38: sem conexão | D38: Vinicius da Silva Dos Santos | E38: Corporativo | F38: 9 | G38: 295423 | H38: 200 | I38: LINK DE DADOS | J38: 218297 | K38: J FEITOSA SILVA FILHO LOJAS SANTA MARIA | L38: 05.017.606/0001-53 | M38: 46027.431 | N38: 46028.419 | O38: PENDENTE VALIDAÇÃO | P38: CMO - Reparo | Q38: Portal do Cliente | R38: Rompimento de Fibra | U38: 166879 | V38: 166879 | W38: 166879 | X38: MA | Y38: SAO LUIS | AA38: Entre 4h e 8h | AB38: 23.633333 | AC38: 17.316667 | AD38: 6.316666 | AE38: 0.233333 | AF38: 0 | AG38: 6.083333 | AH38: 6.083333 | AI38: 6.05 | AJ38: 0.033333 | AK38: 0 | AL38: 45293.489 | AM38: 733 | AN38: Maior que 15d pós ativação | AO38: SLS/L2L/218297/9 | AP38: MA, PA, PI E AP | AQ38: C.32 - Maranhão | AR38: Wellington Marcio | AT38: S02 | AU38: 2026 | AV38: 1 | AW38: MA CAP | AX38: 1 | AY38: 0 | BT38: MA CAP | BU38: 1 | BV38: 0
A39: 5746745 | B39: 05012026-22407 | C39: GR NET TELECOMUNICACOES LTDA GR NET || Indisponibilidade || NMB/IPD/214735/1 | D39: Stephanie Aparecida Arthur | E39: Provedores | F39: 1 | G39: 269667 | H39: 2310 | I39: INTERNET DEDICADA - SCM(Wire) | J39: 214735 | K39: GR NET TELECOMUNICACOES LTDA GR NET | L39: 40.089.789/0001-13 | M39: 46027.538 | N39: 46028.438 | O39: PENDENTE VALIDAÇÃO | P39: CMO - Reparo | Q39: Telefone | R39: Normalizado Sem Intervenção | T39: ONLINE NORTE TELECOM LTDA | U39: 167037 | V39: 167037, 167049 | W39: 167037 | X39: PA | Y39: NOVA TIMBOTEUA | AA39: Até 4h | AB39: 21.566667 | AC39: 19.583333 | AD39: 1.983334 | AE39: 1.233334 | AF39: 0 | AG39: 0.75 | AH39: 0.75 | AI39: 0.716667 | AJ39: 0.033333 | AK39: 0 | AL39: 36526 | AM39: 9501 | AN39: Maior que 15d pós ativação | AO39: NMB/IPD/214735/1 | AP39: MA, PA, PI E AP | AQ39: C.28 - Norte | AR39: Wellington Marcio | AT39: S02 | AU39: 2026 | AV39: 1 | AW39: PA INT | AX39: 1 | AY39: 0 | BT39: PA INT | BU39: 1 | BV39: 0
A40: 5743995 | B40: 03012026-19233 | C40: ALERTA: CLI | MPMA.SLS.CONCENTRADOR.REDUNDANTE.L2L.149307.22 - FALHA | D40: Vinicius da Silva Dos Santos | E40: Público | F40: 22 | G40: 279675 | H40: 0 | I40: INTERNET DEDICADA - SCM(Wire) | J40: 149307 | K40: ESTADO DO MARANHAO PROCURADORIA GERAL DA JUSTICA PROCURADORIA GERAL DA JUSTICA | L40: 05.483.912/0001-85 | M40: 46025.563 | N40: 46028.496 | O40: PENDENTE VALIDAÇÃO | P40: CMO - Reparo | Q40: Email | R40: Ajuste de Atenuação | U40: 166537 | V40: 166537 | W40: 166537 | X40: MA | Y40: SAO LUIS | AA40: Entre 4h e 8h | AB40: 70.333332 | AC40: 64.383333 | AD40: 5.949999 | AE40: 1.233333 | AF40: 0 | AG40: 4.716666 | AH40: 4.716666 | AI40: 1.816666 | AJ40: 2.9 | AK40: 0 | AL40: 44767 | AM40: 1258 | AN40: Maior que 15d pós ativação | AO40: SLS/IPD/149307/22 | AP40: MA, PA, PI E AP | AQ40: C.32 - Maranhão | AR40: Wellington Marcio | AT40: S02 | AU40: 2026 | AV40: 1 | AW40: MA CAP | AX40: 1 | AY40: 0 | BT40: MA CAP | BU40: 1 | BV40: 0
A41: 5747145 | B41: 05012026-88814 | C41: GESTION SERVICES LTDA | INDISPONIBILIDADE | SLS/IPD/218805/1 | D41: Julia Ferreira Costa Silva | E41: Corporativo | F41: 1 | G41: 298751 | H41: 314.39 | I41: LINK DEDICADO DE INTERNET | J41: 218805 | K41: GESTION SERVICES LTDA | L41: 48.401.636/0001-71 | M41: 46027.637 | N41: 46028.529 | O41: PENDENTE VALIDAÇÃO | P41: CMO - Reparo | Q41: Chat | R41: Rompimento de Fibra | U41: 167219 | V41: 167079, 167175, 167219, 167571 | W41: 167571 | X41: MA | Y41: SAO LUIS | AA41: Entre 8h e 12h | AB41: 21.35 | AC41: 12.983333 | AD41: 8.366667 | AE41: 0.233333 | AF41: 0 | AG41: 8.133334 | AH41: 8.133334 | AI41: 8.1 | AJ41: 0.033334 | AK41: 0 | AL41: 45288.672 | AM41: 738 | AN41: Maior que 15d pós ativação | AO41: SLS/IPD/218805/1 | AP41: MA, PA, PI E AP | AQ41: C.32 - Maranhão | AR41: Wellington Marcio | AT41: S02 | AU41: 2026 | AV41: 1 | AW41: MA CAP | AX41: 0 | AY41: 0 | BT41: MA CAP | BU41: 0 | BV41: 0
A42: 5746495 | B42: 05012026-22793 | C42: INOVANET EMPREENDIMENTOS LTDA. INOVANET | INDISPONIBILIDADE | SLS/L2L/133341/21 | D42: Laura Beatriz de Sibia Santos | E42: Provedores | F42: 21 | G42: 342799 | H42: 250 | I42: L2L Metro | J42: 133341 | K42: INOVANET EMPREENDIMENTOS LTDA. INOVANET | L42: 21.278.402/0001-22 | M42: 46027.484 | N42: 46028.547 | O42: PENDENTE VALIDAÇÃO | P42: CMO - Reparo | Q42: Chat | R42: Ajuste de Atenuação | U42: 167217 | V42: 166951, 167217 | W42: 167217 | X42: MA | Y42: SAO LUIS | AA42: Entre 4h e 8h | AB42: 25.400001 | AC42: 17.266667 | AD42: 8.133334 | AE42: 1.116667 | AF42: 0 | AG42: 7.016667 | AH42: 7.016667 | AI42: 6.983333 | AJ42: 0.033334 | AK42: 0 | AL42: 45966.724 | AM42: 60 | AN42: Maior que 15d pós ativação | AO42: SLS/L2L/133341/21 | AP42: MA, PA, PI E AP | AQ42: C.32 - Maranhão | AR42: Wellington Marcio | AT42: S02 | AU42: 2026 | AV42: 1 | AW42: MA CAP | AX42: 1 | AY42: 0 | BT42: MA CAP | BU42: 1 | BV42: 0
A43: 5746145 | B43: 05012026-43155 | C43: BANCO DO NORDESTE DO BRASIL SA BNB || INDISPONÍVEL || PCR5011992 | D43: Stephanie Aparecida Arthur | E43: Público | F43: 107 | G43: 100653 | H43: 788.96 | I43: SUPER LIGEIRO FIBRA PLUS | J43: 6971 | K43: BANCO DO NORDESTE DO BRASIL SA BNB | L43: 07.237.373/0001-20 | M43: 46027.423 | N43: 46028.648 | O43: PENDENTE VALIDAÇÃO | P43: CMO - Reparo | Q43: Chat | R43: Rompimento de Fibra | U43: 166883 | V43: 166883 | W43: 166883 | X43: PI | Y43: PIRACURUCA | AA43: Entre 4h e 8h | AB43: 29.35 | AC43: 23.983333 | AD43: 5.366667 | AE43: 0.25 | AF43: 0 | AG43: 5.116667 | AH43: 5.116667 | AI43: 4.933334 | AJ43: 0.183333 | AK43: 0 | AL43: 43599.445 | AM43: 2427 | AN43: Maior que 15d pós ativação | AO43: PCR/FBR/6971/107 | AP43: MA, PA, PI E AP | AQ43: C.31 - Piaui | AR43: Wellington Marcio | AT43: S02 | AU43: 2026 | AV43: 1 | AW43: PI INT | AX43: 1 | AY43: 0 | BT43: PI INT | BU43: 1 | BV43: 0
A44: 5746055 | B44: 05012026-96588 | C44: LACMAR LABORATORIO DE ANALISES CLINICAS DO MARANHAO | INDISPONIBILIDADE | 204321/9 | D44: Stephanie Aparecida Arthur | E44: Corporativo | F44: 9 | G44: 302283 | H44: 360.5 | I44: LINK DEDICADO DE INTERNET | J44: 204321 | K44: LACMAR LABORATORIO DE ANALISES CLINICAS DO MARANHAO LTDA LACMAR | L44: 20.815.524/0001-48 | M44: 46027.406 | N44: 46028.677 | O44: PENDENTE VALIDAÇÃO | P44: CMO - Reparo | Q44: Chat | R44: Rompimento de Fibra | U44: 167209 | V44: 166839, 167209 | W44: 167209 | X44: MA | Y44: SAO LUIS | AA44: Maior que 24h | AB44: 30.45 | AC44: 4.8 | AD44: 25.65 | AE44: 0.116667 | AF44: 0 | AG44: 25.533333 | AH44: 25.533333 | AI44: 25.35 | AJ44: 0.183333 | AK44: 0 | AL44: 45428 | AM44: 599 | AN44: Maior que 15d pós ativação | AO44: SLS/IPD/204321/9 | AP44: MA, PA, PI E AP | AQ44: C.32 - Maranhão | AR44: Wellington Marcio | AT44: S02 | AU44: 2026 | AV44: 1 | AW44: MA CAP | AX44: 0 | AY44: 1 | BT44: MA CAP | BU44: 0 | BV44: 1
A45: 5750435 | B45: 06012026-48639 | C45: IAP COSMETICOS LTDA | indisponível | TSA/IPD/84093/1 | D45: INGRID DA SILVA CALIXTO SANTANA | E45: Corporativo | F45: 1 | G45: 102583 | H45: 385.96 | I45: LINK DEDICADO DE INTERNET | J45: 84093 | K45: IAP COSMETICOS LTDA IAP COSMETICOS | L45: 05.346.644/0006-64 | M45: 46028.661 | N45: 46028.752 | O45: PENDENTE VALIDAÇÃO | P45: CMO - Reparo | Q45: Chat | R45: Rompimento de Fibra | U45: 167891 | V45: 167891 | W45: 167891 | X45: PI | Y45: TERESINA | AA45: Até 4h | AB45: 2.116667 | AC45: 0.116667 | AD45: 2 | AE45: 0.3 | AF45: 0 | AG45: 1.7 | AH45: 1.7 | AI45: 1.433333 | AJ45: 0.266667 | AK45: 0 | AL45: 43538.744 | AM45: 2489 | AN45: Maior que 15d pós ativação | AO45: TSA/IPD/84093/1 | AP45: MA, PA, PI E AP | AQ45: C.31 - Piaui | AR45: Wellington Marcio | AT45: S02 | AU45: 2026 | AV45: 1 | AW45: PI CAP | AX45: 1 | AY45: 0 | BT45: PI CAP | BU45: 1 | BV45: 0
A46: 5749481 | B46: 06012026-31713 | C46: Abertura de reparo - Chamado Equinix 1-255758912404 |Circuito: MPA0-L2LAN-00136119-00012| Cliente final: COMPANHIA DE ELETRICIDADE DO AMAPA CEA | D46: Laura Beatriz de Sibia Santos | E46: Operadoras | F46: 12 | G46: 296177 | H46: 3330.9 | I46: LINK DE DADOS | J46: 229111 | K46: EQUINIX DO BRASIL TELECOMUNICACOES LTDA EQUINIX DO BRASIL TELECOMUNICACOES LTDA | L46: 10.496.781/0004-53 | M46: 46028.41 | N46: 46029.306 | O46: ANALISAR RESPOSTA | P46: CMO - Reparo | Q46: Email | R46: Ajuste de Atenuação | X46: AP | Y46: MACAPA | AA46: Entre 4h e 8h | AB46: 21.416667 | AC46: 13.516667 | AD46: 7.9 | AE46: 1.1 | AF46: 0 | AG46: 6.8 | AH46: 6.8 | AI46: 6.65 | AJ46: 0.15 | AK46: 0 | AL46: 45320 | AM46: 708 | AN46: Maior que 15d pós ativação | AO46: MPA/L2L/229111/12 | AP46: MA, PA, PI E AP | AQ46: C.28 - Norte | AR46: Wellington Marcio | AT46: S02 | AU46: 2026 | AV46: 1 | AW46: AP | AX46: 1 | AY46: 0 | BT46: AP | BU46: 1 | BV46: 0
A47: 5749699 | B47: 06012026-53861 | C47: ALERTA: CLI | CONDOMINIO SHOPPING.AIU.ANANINDEUA.IPD.225005.1 - FALHA | D47: Joao Victor Santos Medeiros | E47: Corporativo | F47: 1 | G47: 330947 | H47: 800 | I47: IP CONNECT Metro | J47: 225005 | K47: CONDOMINIO DO SHOPPING METROPOLE ANANINDEUA CONDOMINIO DO SHOPPING METROPOLE ANANINDEUA | L47: 30.838.194/0001-60 | M47: 46028.459 | N47: 46029.326 | O47: PENDENTE VALIDAÇÃO | P47: CMO - Reparo | Q47: Email | R47: Configuração | U47: 167673 | V47: 167673 | W47: 167673 | X47: PA | Y47: ANANINDEUA | AA47: Até 4h | AB47: 20.749999 | AC47: 17.816666 | AD47: 2.933333 | AE47: 1.216666 | AF47: 0 | AG47: 1.716667 | AH47: 1.716667 | AI47: 1.7 | AJ47: 0.016667 | AK47: 0 | AL47: 45713 | AM47: 315 | AN47: Maior que 15d pós ativação | AO47: AIU/IPD/225005/1 | AP47: MA, PA, PI E AP | AQ47: C.28 - Norte | AR47: Wellington Marcio | AT47: S02 | AU47: 2026 | AV47: 1 | AW47: PA CAP | AX47: 1 | AY47: 0 | BT47: PA CAP | BU47: 1 | BV47: 0
A48: 5749599 | B48: 06012026-83131 | C48: APODI DISTRIBUICAO E LOGISTICA LTDA | INDISPONIBILIDADE | PCZ/IPD/203325/1 | D48: Vinicius da Silva Dos Santos | E48: Corporativo | F48: 1 | G48: 249009 | H48: 600 | I48: LINK DEDICADO DE INTERNET | J48: 203325 | K48: APODI DISTRIBUICAO E LOGISTICA LTDA | L48: 29.190.494/0009-53 | M48: 46028.441 | N48: 46029.346 | O48: PENDENTE VALIDAÇÃO | P48: CMO - Reparo | Q48: Chat | R48: Ajuste de Atenuação | U48: 167591 | V48: 167591 | W48: 167591 | X48: PI | Y48: PICOS | AA48: Entre 8h e 12h | AB48: 21.683333 | AC48: 13.25 | AD48: 8.433333 | AE48: 0.15 | AF48: 0 | AG48: 8.283333 | AH48: 8.283333 | AI48: 8.266666 | AJ48: 0.016667 | AK48: 0 | AL48: 44568 | AM48: 1460 | AN48: Maior que 15d pós ativação | AO48: PCZ/IPD/203325/1 | AP48: MA, PA, PI E AP | AQ48: C.31 - Piaui | AR48: Wellington Marcio | AT48: S02 | AU48: 2026 | AV48: 1 | AW48: PI INT | AX48: 0 | AY48: 0 | BT48: PI INT | BU48: 0 | BV48: 0
A49: 5737535 | B49: 30122025-23911 | C49: Atendimento para: UEB MARIA JOSE SERRAO - SLS-216233-00235 | D49: Vinicius da Silva Dos Santos | E49: Público | F49: 235 | G49: 286311 | H49: 364.96 | I49: LINK DE DADOS | J49: 216233 | K49: MUNICIPIO DE SAO LUIS SEMIT | L49: 06.307.102/0001-30 | M49: 46021.522 | N49: 46029.362 | O49: PENDENTE VALIDAÇÃO | P49: CMO - Reparo | Q49: Email | R49: Rompimento de Fibra | U49: 167225 | V49: 167225 | W49: 167225 | X49: MA | Y49: SAO LUIS | AA49: Entre 8h e 12h | AB49: 188.08333 | AC49: 29.766667 | AD49: 158.31667 | AE49: 148.4 | AF49: 0 | AG49: 9.916666 | AH49: 9.916666 | AI49: 9.45 | AJ49: 0.466666 | AK49: 0 | AL49: 44921 | AM49: 1100 | AN49: Maior que 15d pós ativação | AO49: SLS/L2L/218787/235 | AP49: MA, PA, PI E AP | AQ49: C.32 - Maranhão | AR49: Wellington Marcio | AT49: S02 | AU49: 2026 | AV49: 1 | AW49: MA CAP | AX49: 0 | AY49: 0 | BT49: MA CAP | BU49: 0 | BV49: 0
A50: 5741947 | B50: 01012026-76706 | C50: Atendimento para: UEB MINDINHO - POLO - SLS-216233-00331 | D50: Vinicius da Silva Dos Santos | E50: Público | F50: 12 | G50: 275211 | H50: 398.82 | I50: LINK DE DADOS | J50: 216233 | K50: MUNICIPIO DE SAO LUIS SEMIT | L50: 06.307.102/0001-30 | M50: 46023.924 | N50: 46029.364 | O50: PENDENTE VALIDAÇÃO | P50: CMO - Reparo | Q50: Email | R50: Ajuste de Atenuação | U50: 167695 | V50: 165977, 165991, 166527, 167695 | W50: 166527, 167695 | X50: MA | Y50: SAO LUIS | AA50: Entre 12h e 24h | AB50: 130.41667 | AC50: 116.58334 | AD50: 13.833335 | AE50: 0.833334 | AF50: 0 | AG50: 13.000001 | AH50: 13.000001 | AI50: 11.650001 | AJ50: 1.35 | AK50: 0 | AL50: 44986 | AM50: 1037 | AN50: Maior que 15d pós ativação | AO50: SLS/L2L/216233/12 | AP50: MA, PA, PI E AP | AQ50: C.32 - Maranhão | AR50: Wellington Marcio | AT50: S02 | AU50: 2026 | AV50: 1 | AW50: MA CAP | AX50: 0 | AY50: 0 | BT50: MA CAP | BU50: 0 | BV50: 0
A51: 5744277 | B51: 03012026-54555 | C51: Atendimento para: CS GENESIO RAMOS FILHO - SLS-216233-00061 | D51: Vinicius da Silva Dos Santos | E51: Público | F51: 61 | G51: 275367 | H51: 368.16 | I51: LINK DE DADOS | J51: 218791 | K51: FUNDO MUNICIPAL DE SAUDE DE SAO LUIS MARANHAO | L51: 13.816.886/0001-98 | M51: 46025.716 | N51: 46029.402 | O51: PENDENTE VALIDAÇÃO | P51: CMO - Reparo | Q51: Email | R51: Ajuste de Atenuação | U51: 167613 | V51: 167613 | W51: 167613 | X51: MA | Y51: SAO LUIS | Z51: 523084 | AA51: Entre 4h e 8h | AB51: 88.416666 | AC51: 16.75 | AD51: 71.666666 | AE51: 65.65 | AF51: 64 | AG51: 6.016666 | AH51: 70.016666 | AI51: 5.883333 | AJ51: 0.133333 | AK51: 0 | AL51: 44853.544 | AM51: 1172 | AN51: Maior que 15d pós ativação | AO51: SLS/L2L/218791/61 | AP51: MA, PA, PI E AP | AQ51: C.32 - Maranhão | AR51: Wellington Marcio | AT51: S02 | AU51: 2026 | AV51: 1 | AW51: MA CAP | AX51: 1 | AY51: 0 | BT51: MA CAP | BU51: 1 | BV51: 0
A52: 5746515 | B52: 05012026-95270 | C52: Atendimento para: CS COHAB ANIL I - VLAN 3617 SLS-216233-00098 | D52: Vinicius da Silva Dos Santos | E52: Público | F52: 98 | G52: 275499 | H52: 368.16 | I52: LINK DE DADOS | J52: 218791 | K52: FUNDO MUNICIPAL DE SAUDE DE SAO LUIS MARANHAO | L52: 13.816.886/0001-98 | M52: 46027.487 | N52: 46029.403 | O52: PENDENTE VALIDAÇÃO | P52: CMO - Reparo | Q52: Email | R52: Normalizado Sem Intervenção | U52: 167631 | V52: 167631 | W52: 167631 | X52: MA | Y52: SAO LUIS | Z52: 523787 | AA52: Até 4h | AB52: 45.866667 | AC52: 19.75 | AD52: 26.116667 | AE52: 22.116667 | AF52: 21.433333 | AG52: 4 | AH52: 25.433333 | AI52: 3.7 | AJ52: 0.3 | AK52: 0 | AL52: 44863.652 | AM52: 1163 | AN52: Maior que 15d pós ativação | AO52: SLS/L2L/218791/98 | AP52: MA, PA, PI E AP | AQ52: C.32 - Maranhão | AR52: Wellington Marcio | AT52: S02 | AU52: 2026 | AV52: 1 | AW52: MA CAP | AX52: 1 | AY52: 0 | BT52: MA CAP | BU52: 1 | BV52: 0
A53: 5747279 | B53: 05012026-89257 | C53: LINK BANDA LARGA LOJA 47 - HOLANDESES INOPERANTE | D53: Vinicius da Silva Dos Santos | E53: Corporativo | F53: 114 | G53: 297253 | H53: 300 | I53: LINK DE DADOS | J53: 13955 | K53: PFM COMERCIAL LTDA - CASA FREITAS | L53: 01.740.627/0001-41 | M53: 46027.657 | N53: 46029.41 | O53: PENDENTE VALIDAÇÃO | P53: CMO - Reparo | Q53: Portal do Cliente | R53: Ajuste de Atenuação | U53: 167211 | V53: 167109, 167211 | W53: 167211 | X53: MA | Y53: SAO LUIS | AA53: Entre 12h e 24h | AB53: 42.033333 | AC53: 17.883333 | AD53: 24.15 | AE53: 0.166667 | AF53: 0 | AG53: 23.983333 | AH53: 23.983333 | AI53: 23.65 | AJ53: 0.333333 | AK53: 0 | AL53: 45342 | AM53: 685 | AN53: Maior que 15d pós ativação | AO53: SLS/L2L/13955/114 | AP53: MA, PA, PI E AP | AQ53: C.32 - Maranhão | AR53: Wellington Marcio | AT53: S02 | AU53: 2026 | AV53: 1 | AW53: MA CAP | AX53: 0 | AY53: 0 | BT53: MA CAP | BU53: 0 | BV53: 0
A54: 5749961 | B54: 06012026-31572 | C54: FUNDO MUNICIPAL DE SAUDE DE SAO LUIS MARANHAO | INDISPONIBILIDADE | SLS/L2L/218791/34 | D54: Stephanie Aparecida Arthur | E54: Público | F54: 34 | G54: 275255 | H54: 525.95 | I54: LINK DE DADOS | J54: 218791 | K54: FUNDO MUNICIPAL DE SAUDE DE SAO LUIS MARANHAO | L54: 13.816.886/0001-98 | M54: 46028.518 | N54: 46029.443 | O54: PENDENTE VALIDAÇÃO | P54: CMO - Reparo | Q54: Chat | R54: Normalizado Sem Intervenção | U54: 167701 | V54: 167701 | X54: MA | Y54: SAO LUIS | AA54: Entre 8h e 12h | AB54: 22.166667 | AC54: 12.616667 | AD54: 9.55 | AE54: 0.433333 | AF54: 0 | AG54: 9.116667 | AH54: 9.116667 | AI54: 8.916667 | AJ54: 0.2 | AK54: 0 | AL54: 44862.561 | AM54: 1165 | AN54: Maior que 15d pós ativação | AO54: SLS/L2L/218791/34 | AP54: MA, PA, PI E AP | AQ54: C.32 - Maranhão | AR54: Wellington Marcio | AT54: S02 | AU54: 2026 | AV54: 1 | AW54: MA CAP | AX54: 0 | AY54: 0 | BT54: MA CAP | BU54: 0 | BV54: 0
A55: 5749815 | B55: 06012026-38841 | C55: Atendimento para: SEMURH - BLITZ URBANA - VLAN-1317 SLS-216233-00030 | D55: Vanessa Alves Ferreira | E55: Público | F55: 30 | G55: 275247 | H55: 569.71 | I55: LINK DE DADOS | J55: 216233 | K55: MUNICIPIO DE SAO LUIS SEMIT | L55: 06.307.102/0001-30 | M55: 46028.494 | N55: 46029.49 | O55: PENDENTE VALIDAÇÃO | P55: CMO - Reparo | Q55: Email | R55: Rompimento de Fibra | U55: 167993 | V55: 167671, 167675, 167993 | W55: 167993 | X55: MA | Y55: SAO LUIS | AA55: Entre 4h e 8h | AB55: 23.849999 | AC55: 16.383333 | AD55: 7.466666 | AE55: 0.183333 | AF55: 0 | AG55: 7.283333 | AH55: 7.283333 | AI55: 6.966666 | AJ55: 0.316667 | AK55: 0 | AL55: 44838 | AM55: 1190 | AN55: Maior que 15d pós ativação | AO55: SLS/L2L/216233/30 | AP55: MA, PA, PI E AP | AQ55: C.32 - Maranhão | AR55: Wellington Marcio | AT55: S02 | AU55: 2026 | AV55: 1 | AW55: MA CAP | AX55: 1 | AY55: 0 | BT55: MA CAP | BU55: 1 | BV55: 0
A56: 5732805 | B56: 29122025-37448 | C56: REPARO | D56: Laura Beatriz de Sibia Santos | E56: Corporativo | F56: 22 | G56: 322683 | H56: 399 | I56: LINK DEDICADO DE INTERNET | J56: 219061 | K56: SOLDI PROMOTORA DE VENDAS LTDA GRUPO AGIBANK | L56: 07.249.846/0001-09 | M56: 46020.377 | N56: 46029.517 | O56: PENDENTE VALIDAÇÃO | P56: CMO - Reparo | Q56: Portal do Cliente | R56: Ajuste de Atenuação | U56: 167605 | V56: 164613, 167605, 167877 | W56: 167877 | X56: MA | Y56: CHAPADINHA | Z56: 514664 | AA56: Entre 12h e 24h | AB56: 219.26667 | AC56: 18.916666 | AD56: 200.35 | AE56: 184.15 | AF56: 182.96667 | AG56: 16.200001 | AH56: 199.16667 | AI56: 13.9 | AJ56: 2.300001 | AK56: 0 | AL56: 45535.767 | AM56: 484 | AN56: Maior que 15d pós ativação | AO56: CHI/IPD/219061/22 | AP56: MA, PA, PI E AP | AQ56: C.32 - Maranhão | AR56: Wellington Marcio | AT56: S02 | AU56: 2026 | AV56: 1 | AW56: MA INT | AX56: 0 | AY56: 0 | BT56: MA INT | BU56: 0 | BV56: 0
A57: 5746543 | B57: 05012026-75579 | C57: Indisponibilidade de Link | D57: Vinicius da Silva Dos Santos | E57: Corporativo | F57: 1 | G57: 331211 | H57: 800 | I57: IP CONNECT Metro | J57: 225435 | K57: CONDOMINIO RESERVA DA ILHA SHOPPING DA ILHA | L57: 17.975.106/0001-03 | M57: 46027.488 | N57: 46029.553 | O57: PENDENTE VALIDAÇÃO | P57: CMO - Reparo | Q57: Portal do Cliente | R57: Ajuste de Atenuação | U57: 167215 | V57: 166929, 167215 | W57: 167215 | X57: MA | Y57: SAO LUIS | AA57: Entre 8h e 12h | AB57: 49.450001 | AC57: 38.933333 | AD57: 10.516668 | AE57: 0.2 | AF57: 0 | AG57: 10.316668 | AH57: 10.316668 | AI57: 10.233334 | AJ57: 0.083334 | AK57: 0 | AL57: 45796.459 | AM57: 231 | AN57: Maior que 15d pós ativação | AO57: SLS/IPD/225435/1 | AP57: MA, PA, PI E AP | AQ57: C.32 - Maranhão | AR57: Wellington Marcio | AT57: S02 | AU57: 2026 | AV57: 1 | AW57: MA CAP | AX57: 0 | AY57: 0 | BT57: MA CAP | BU57: 0 | BV57: 0
A58: 5756165 | B58: 07012026-80796 | C58: ALERTA: CLI | TJMA.SLS.POSTO.HIDRO.PORTUARIO.L3VPN.49495.299 - FALHA | D58: HOANNA MARIA DA SILVA ALBUQUERQUE | E58: Público | F58: 299 | G58: 285731 | H58: 512.08 | I58: TRANSPORTE LAN TO LAN(Wire) | J58: 49495 | K58: FUNDO ESPECIAL DE MODERNIZACAO E REAPARELHAMENTO | L58: 04.408.070/0001-34 | M58: 46029.613 | N58: 46029.647 | O58: AGUARDANDO DISPONIBILIDADE TECNICA | P58: CMO - Reparo | Q58: Email | R58: Falha Elétrica Cliente | X58: MA | Y58: SAO LUIS | AA58: Até 4h | AB58: 0.783334 | AC58: 0 | AD58: 0.783334 | AE58: 0.316667 | AF58: 0 | AG58: 0.466667 | AI58: 0.05 | AJ58: 0.416667 | AK58: 0 | AL58: 44862 | AM58: 1167 | AN58: Maior que 15d pós ativação | AO58: SLS/L2L/49495/299 | AP58: MA, PA, PI E AP | AQ58: C.32 - Maranhão | AR58: Wellington Marcio | AT58: S02 | AU58: 2026 | AV58: 1 | AW58: MA CAP | AX58: 1 | AY58: 0 | BT58: MA CAP | BU58: 1 | BV58: 0
A59: 5747237 | B59: 05012026-49450 | C59: MARDISA AUTOMOVEIS LTDA | INDISPONIBILIDADE | SLS/IPD/225015/1 | D59: Stephanie Aparecida Arthur | E59: Corporativo | F59: 1 | G59: 329639 | H59: 600 | I59: IP CONNECT Metro | J59: 225015 | K59: MARDISA AUTOMOVEIS LTDA | L59: 09.043.453/0003-31 | M59: 46027.652 | N59: 46029.66 | O59: PENDENTE VALIDAÇÃO | P59: CMO - Reparo | Q59: Chat | R59: Normalizado Sem Intervenção | U59: 167223 | V59: 167223 | X59: MA | Y59: SAO LUIS | AA59: Entre 4h e 8h | AB59: 48.133332 | AC59: 40.666666 | AD59: 7.466666 | AE59: 0.533333 | AF59: 0 | AG59: 6.933333 | AH59: 6.933333 | AI59: 6.65 | AJ59: 0.283333 | AK59: 0 | AL59: 45645.372 | AM59: 382 | AN59: Maior que 15d pós ativação | AO59: SLS/IPD/225015/1 | AP59: MA, PA, PI E AP | AQ59: C.32 - Maranhão | AR59: Wellington Marcio | AT59: S02 | AU59: 2026 | AV59: 1 | AW59: MA CAP | AX59: 1 | AY59: 0 | BT59: MA CAP | BU59: 1 | BV59: 0
A60: 5747341 | B60: 05012026-10547 | C60: Atendimento para: UEB ENS FUND GOVERNADOR LEONEL BRIZOLA - Anexo Brizolinha - SLS-216233-00189 | D60: Stephanie Aparecida Arthur | E60: Público | F60: 189 | G60: 285915 | H60: 364.95 | I60: LINK DE DADOS | J60: 218787 | K60: MUNICIPIO DE SAO LUIS SEMED | L60: 06.307.102/0002-11 | M60: 46027.667 | N60: 46029.662 | O60: PENDENTE VALIDAÇÃO | P60: CMO - Reparo | Q60: Email | R60: Rompimento de Fibra | U60: 167227 | V60: 167227 | W60: 167227 | X60: MA | Y60: SAO LUIS | AA60: Entre 4h e 8h | AB60: 47.783335 | AC60: 40.916667 | AD60: 6.866668 | AE60: 0.1 | AF60: 0 | AG60: 6.766668 | AH60: 6.766668 | AI60: 6.633334 | AJ60: 0.133334 | AK60: 0 | AL60: 44918 | AM60: 1109 | AN60: Maior que 15d pós ativação | AO60: SLS/L2L/218787/189 | AP60: MA, PA, PI E AP | AQ60: C.32 - Maranhão | AR60: Wellington Marcio | AT60: S02 | AU60: 2026 | AV60: 1 | AW60: MA CAP | AX60: 1 | AY60: 0 | BT60: MA CAP | BU60: 1 | BV60: 0
A61: 5749797 | B61: 06012026-93282 | C61: MUNICIPIO DE SAO LUIS SEMED | INDISPONIBILIDADE | SLS/L2L/218787/367 | D61: Vanessa Alves Ferreira | E61: Público | F61: 367 | G61: 286775 | H61: 364.96 | I61: LINK DE DADOS | J61: 218787 | K61: MUNICIPIO DE SAO LUIS SEMED | L61: 06.307.102/0002-11 | M61: 46028.481 | N61: 46029.666 | O61: PENDENTE CLIENTE | P61: CMO - Reparo | Q61: Chat | R61: Ação Cliente | U61: 167991 | V61: 167657, 167991 | X61: MA | Y61: SAO LUIS | AA61: Entre 8h e 12h | AB61: 28.366667 | AC61: 19.5 | AD61: 8.866667 | AE61: 0.083333 | AF61: 0 | AG61: 8.783334 | AH61: 8.783334 | AI61: 8.433334 | AJ61: 0.35 | AK61: 0 | AL61: 44943 | AM61: 1085 | AN61: Maior que 15d pós ativação | AO61: SLS/L2L/218787/367 | AP61: MA, PA, PI E AP | AQ61: C.32 - Maranhão | AR61: Wellington Marcio | AT61: S02 | AU61: 2026 | AV61: 1 | AW61: MA CAP | AX61: 0 | AY61: 0 | BT61: MA CAP | BU61: 0 | BV61: 0
A62: 5749931 | B62: 06012026-43078 | C62: MBA/IPD/60121/3 | D62: Stephanie Aparecida Arthur | E62: Corporativo | F62: 3 | G62: 303081 | H62: 399 | I62: LINK DEDICADO DE INTERNET | J62: 60121 | K62: PROMIL PROMOTORA DE VENDAS LTDA GRUPO AGIBANK | L62: 09.093.910/0001-30 | M62: 46028.51 | N62: 46029.67 | O62: PENDENTE VALIDAÇÃO | P62: CMO - Reparo | Q62: Portal do Cliente | R62: Rompimento de Fibra | U62: 167753 | V62: 167753 | W62: 167753 | X62: PA | Y62: MARABA | AA62: Entre 4h e 8h | AB62: 27.783334 | AC62: 23.05 | AD62: 4.733334 | AE62: 0.183333 | AF62: 0 | AG62: 4.550001 | AH62: 4.550001 | AI62: 4.233334 | AJ62: 0.316667 | AK62: 0 | AL62: 45502 | AM62: 526 | AN62: Maior que 15d pós ativação | AO62: MBA/IPD/60121/3 | AP62: MA, PA, PI E AP | AQ62: C.28 - Norte | AR62: Wellington Marcio | AT62: S02 | AU62: 2026 | AV62: 1 | AW62: PA INT | AX62: 1 | AY62: 0 | BT62: PA INT | BU62: 1 | BV62: 0
A63: 5750695 | B63: 06012026-62151 | C63: M E L SERVICOS EM SAUDE LTDA SUPER CLINICA | INDISPONIBILIDADE | SLS/L2L/218289/1 | D63: INGRID DA SILVA CALIXTO SANTANA | E63: Corporativo | F63: 1 | G63: 294383 | H63: 377.91 | I63: LINK DE DADOS | J63: 218289 | K63: M E L SERVICOS EM SAUDE LTDA SUPER CLINICA | L63: 05.596.740/0004-07 | M63: 46028.741 | N63: 46029.69 | O63: PENDENTE VALIDAÇÃO | P63: CMO - Reparo | Q63: Chat | R63: Rompimento de Fibra | U63: 168007 | V63: 168007, 168009, 168011, 168181, 168185, 168189 | W63: 168189 | X63: MA | Y63: SAO LUIS | AA63: Entre 8h e 12h | AB63: 22.683333 | AC63: 14.216667 | AD63: 8.466666 | AE63: 0.15 | AF63: 0 | AG63: 8.316666 | AH63: 8.316666 | AI63: 8.116666 | AJ63: 0.2 | AK63: 0 | AL63: 45205 | AM63: 823 | AN63: Maior que 15d pós ativação | AO63: SLS/L2L/218289/1 | AP63: MA, PA, PI E AP | AQ63: C.32 - Maranhão | AR63: Wellington Marcio | AT63: S02 | AU63: 2026 | AV63: 1 | AW63: MA CAP | AX63: 0 | AY63: 0 | BT63: MA CAP | BU63: 0 | BV63: 0
A64: 5749443 | B64: 06012026-93759 | C64: ALERTA: CLI | TJMA.OLNM.FORUM.DE.OLINDA.NOVA.DO.MARANHAO.L3VPN.49495.15 - FALHA | D64: INGRID DA SILVA CALIXTO SANTANA | E64: Público | F64: 15 | G64: 279857 | H64: 616.59 | I64: TRANSPORTE LAN TO LAN(Wire) | J64: 49495 | K64: FUNDO ESPECIAL DE MODERNIZACAO E REAPARELHAMENTO | L64: 04.408.070/0001-34 | M64: 46028.403 | N64: 46029.728 | O64: PENDENTE VALIDAÇÃO | P64: CMO - Reparo | Q64: Email | R64: Rompimento de Fibra | T64: RA TELECOMUNICACOES LTDA. | U64: 168527 | V64: 168527 | W64: 168527 | X64: MA | Y64: NOVA OLINDA DO MARANHAO | AA64: Entre 8h e 12h | AB64: 31.683333 | AC64: 21.016666 | AD64: 10.666667 | AE64: 0.466667 | AF64: 0 | AG64: 10.2 | AH64: 10.2 | AI64: 3.916666 | AJ64: 6.283334 | AK64: 0 | AL64: 44705 | AM64: 1323 | AN64: Maior que 15d pós ativação | AO64: NVMH/L2L/49495/15 | AP64: MA, PA, PI E AP | AQ64: C.32 - Maranhão | AR64: Wellington Marcio | AT64: S02 | AU64: 2026 | AV64: 1 | AW64: MA INT | AX64: 0 | AY64: 0 | BT64: MA INT | BU64: 0 | BV64: 0
A65: 5750001 | B65: 06012026-30609 | C65: Atendimento para: UEB ENS FUND MINISTRO MARIO ANDREAZZA - SLS-216233-00192 | D65: INGRID DA SILVA CALIXTO SANTANA | E65: Público | F65: 192 | G65: 285927 | H65: 350 | I65: LINK DE DADOS | J65: 218787 | K65: MUNICIPIO DE SAO LUIS SEMED | L65: 06.307.102/0002-11 | M65: 46028.529 | N65: 46029.754 | O65: PENDENTE VALIDAÇÃO | P65: CMO - Reparo | Q65: Email | R65: Rompimento de Fibra | U65: 167999 | V65: 167699, 167999 | W65: 167999 | X65: MA | Y65: SAO LUIS | AA65: Entre 12h e 24h | AB65: 29.316666 | AC65: 15.55 | AD65: 13.766666 | AE65: 0.1 | AF65: 0 | AG65: 13.666666 | AH65: 13.666666 | AI65: 13.483333 | AJ65: 0.183333 | AK65: 0 | AL65: 44870.39 | AM65: 1158 | AN65: Maior que 15d pós ativação | AO65: SLS/L2L/218787/192 | AP65: MA, PA, PI E AP | AQ65: C.32 - Maranhão | AR65: Wellington Marcio | AT65: S02 | AU65: 2026 | AV65: 1 | AW65: MA CAP | AX65: 0 | AY65: 0 | BT65: MA CAP | BU65: 0 | BV65: 0
A66: 5754587 | B66: 07012026-56964 | C66: [GLPI #0020374] Você foi Mencionado 0020374 - TIC |ZE-45 Link Inoperante. | D66: Laura Beatriz de Sibia Santos | E66: Público | F66: 32 | G66: 280187 | H66: 926.83 | I66: TRANSPORTE LAN TO LAN(Wire) | J66: 201809 | K66: TRIBUNAL REGIONAL ELEITORAL DO MARANHAO TRE MA | L66: 05.962.421/0001-17 | M66: 46029.417 | N66: 46030.388 | O66: PENDENTE VALIDAÇÃO | P66: CMO - Reparo | Q66: Email | R66: Ajuste de Atenuação | T66: NMA SERVICOS DE TELECOMUNICACOES LTDA | U66: 168803 | V66: 168435, 168803 | W66: 168803 | X66: MA | Y66: PENALVA | AA66: Entre 4h e 8h | AB66: 23.183332 | AC66: 18.633333 | AD66: 4.549999 | AE66: 0.25 | AF66: 0 | AG66: 4.299999 | AH66: 4.299999 | AI66: 3.7 | AJ66: 0.599999 | AK66: 0 | AL66: 44364 | AM66: 1665 | AN66: Maior que 15d pós ativação | AO66: PLV/L2L/201809/32 | AP66: MA, PA, PI E AP | AQ66: C.32 - Maranhão | AR66: Wellington Marcio | AT66: S02 | AU66: 2026 | AV66: 1 | AW66: MA INT | AX66: 1 | AY66: 0 | BT66: MA INT | BU66: 1 | BV66: 0
A67: 5753589 | B67: 07012026-49998 | C67: Solicitação de Reparo - Agência: 28-2201 - SICREDI- Designação: FLO/218115/00001 Ticket Interno: INC8447115 [GIGA+FIBRA] | D67: ANA PAULA DA SILVA SANTOS | E67: Corporativo | F67: 1 | G67: 293657 | H67: 932.99 | I67: LINK DEDICADO DE INTERNET | J67: 218115 | K67: COOPERATIVA DE CREDITO POUPANCA E INVESTIMENTO SICREDI EVOLUCAO UNIDADE DE ATENDIMENTO FLORIANO | L67: 35.571.249/0028-51 | M67: 46029.278 | N67: 46030.401 | O67: PENDENTE VALIDAÇÃO | P67: CMO - Reparo | Q67: Email | R67: Rompimento de Fibra | U67: 168027 | V67: 168027 | W67: 168027 | X67: PI | Y67: FLORIANO | AA67: Até 4h | AB67: 26.833333 | AC67: 22.85 | AD67: 3.983333 | AE67: 0.45 | AF67: 0 | AG67: 3.533333 | AH67: 3.533333 | AI67: 2.333333 | AJ67: 1.2 | AK67: 0 | AL67: 45196.542 | AM67: 832 | AN67: Maior que 15d pós ativação | AO67: FLO/IPD/218115/1 | AP67: MA, PA, PI E AP | AQ67: C.31 - Piaui | AR67: Wellington Marcio | AT67: S02 | AU67: 2026 | AV67: 1 | AW67: PI INT | AX67: 1 | AY67: 0 | BT67: PI INT | BU67: 1 | BV67: 0
A68: 5746693 | B68: 05012026-10570 | C68: Circuito inoperante. | D68: ANA PAULA DA SILVA SANTOS | E68: Público | F68: 21 | G68: 251429 | H68: 510 | I68: LINK DEDICADO DE INTERNET | J68: 203645 | K68: MUNICIPIO DE BELEM BELEM PREF GABINETE DO PREFEITO | L68: 05.055.009/0001-13 | M68: 46027.528 | N68: 46030.403 | O68: PENDENTE VALIDAÇÃO | P68: CMO - Reparo | Q68: Portal do Cliente | R68: Ajuste de Atenuação | U68: 168597 | V68: 166955, 167239, 167957, 168597 | W68: 166955, 167957, 168597 | X68: PA | Y68: BELEM | AA68: Entre 12h e 24h | AB68: 68.833334 | AC68: 45.433333 | AD68: 23.400001 | AE68: 0.233334 | AF68: 0 | AG68: 23.166667 | AH68: 23.166667 | AI68: 22.716667 | AJ68: 0.45 | AK68: 0 | AL68: 45099.589 | AM68: 927 | AN68: Maior que 15d pós ativação | AO68: BLM/IPD/203645/21 | AP68: MA, PA, PI E AP | AQ68: C.28 - Norte | AR68: Wellington Marcio | AT68: S02 | AU68: 2026 | AV68: 1 | AW68: PA CAP | AX68: 0 | AY68: 0 | BT68: PA CAP | BU68: 0 | BV68: 0
A69: 5754081 | B69: 07012026-96899 | C69: LINK INOPERANTE - 2º JUIZADO CÍVEL SLZ- SLS/L2L/49019/93 | D69: Ingrid Alves Lima | E69: Público | F69: 93 | G69: 280013 | H69: 616.59 | I69: TRANSPORTE LAN TO LAN(Wire) | J69: 49495 | K69: FUNDO ESPECIAL DE MODERNIZACAO E REAPARELHAMENTO | L69: 04.408.070/0001-34 | M69: 46029.363 | N69: 46030.423 | O69: PENDENTE VALIDAÇÃO | P69: CMO - Reparo | Q69: Email | R69: Rompimento de Fibra | U69: 168253 | V69: 168253 | W69: 168253 | X69: MA | Y69: SAO LUIS | AA69: Entre 8h e 12h | AB69: 25.383334 | AC69: 16.7 | AD69: 8.683334 | AE69: 0.116667 | AF69: 0 | AG69: 8.566667 | AH69: 8.566667 | AI69: 7.483333 | AJ69: 1.083334 | AK69: 0 | AL69: 44774 | AM69: 1255 | AN69: Maior que 15d pós ativação | AO69: SLS/L2L/49495/93 | AP69: MA, PA, PI E AP | AQ69: C.32 - Maranhão | AR69: Wellington Marcio | AT69: S02 | AU69: 2026 | AV69: 1 | AW69: MA CAP | AX69: 0 | AY69: 0 | BT69: MA CAP | BU69: 0 | BV69: 0
A70: 5749671 | B70: 06012026-85135 | C70: N B S TELECOM LTDA NET | INOPERANTE | AIU/IPD/225007/2 | D70: Stephanie Aparecida Arthur | E70: Provedores | F70: 2 | G70: 332533 | H70: 1390 | I70: IP CONNECT Metro | J70: 225007 | K70: N B S TELECOM LTDA NET BRASIL SERVICOS TELECOM | L70: 18.913.451/0001-85 | M70: 46028.452 | N70: 46030.457 | O70: PENDENTE VALIDAÇÃO | P70: CMO - Reparo | Q70: Chat | R70: Rompimento de Fibra | U70: 167619 | V70: 167619 | W70: 167619 | X70: PA | Y70: ANANINDEUA | AA70: Entre 4h e 8h | AB70: 48.066667 | AC70: 42.05 | AD70: 6.016667 | AE70: 0.116667 | AF70: 0 | AG70: 5.9 | AH70: 5.9 | AI70: 5.766667 | AJ70: 0.133333 | AK70: 0 | AL70: 45757.474 | AM70: 270 | AN70: Maior que 15d pós ativação | AO70: AIU/IPD/225007/2 | AP70: MA, PA, PI E AP | AQ70: C.28 - Norte | AR70: Wellington Marcio | AT70: S02 | AU70: 2026 | AV70: 1 | AW70: PA CAP | AX70: 1 | AY70: 0 | BT70: PA CAP | BU70: 1 | BV70: 0
A71: 5750579 | B71: 06012026-93736 | C71: Alerta de Monitoramento LOJA108 designação GJU-IPD-F-197894 | D71: Stephanie Aparecida Arthur | E71: Corporativo | F71: 70 | G71: 277795 | H71: 367.96 | I71: INTERNET DEDICADA - SCM(Wire) | J71: 212603 | K71: MAGAZINE LILIANI S A GRUPO LILIANI | L71: 11.590.296/0001-64 | M71: 46028.702 | N71: 46030.512 | O71: PENDENTE VALIDAÇÃO | P71: CMO - Reparo | Q71: Email | R71: Rompimento de Fibra | T71: ATEX NET TELECOMUNICAÇÕES LTDA | U71: 167961 | V71: 167961 | W71: 167961 | X71: MA | Y71: GRAJAU | AA71: Até 4h | AB71: 43.383334 | AC71: 42.566667 | AD71: 0.816667 | AE71: 0.8 | AF71: 0 | AG71: 0.016667 | AH71: 0.016667 | AI71: 0 | AJ71: 0.016667 | AK71: 0 | AL71: 43963 | AM71: 2065 | AN71: Maior que 15d pós ativação | AO71: GJU/IPD/212603/70 | AP71: MA, PA, PI E AP | AQ71: C.32 - Maranhão | AR71: Wellington Marcio | AT71: S02 | AU71: 2026 | AV71: 1 | AW71: MA INT | AX71: 1 | AY71: 0 | BT71: MA INT | BU71: 1 | BV71: 0
A72: 5750669 | B72: 06012026-71044 | C72: Atendimento para: SAGARANA I - SLS-216233-00057 | D72: ANA PAULA DA SILVA SANTOS | E72: Público | F72: 57 | G72: 275351 | H72: 364.95 | I72: LINK DE DADOS | J72: 218787 | K72: MUNICIPIO DE SAO LUIS SEMED | L72: 06.307.102/0002-11 | M72: 46028.723 | N72: 46030.523 | O72: PENDENTE VALIDAÇÃO | P72: CMO - Reparo | Q72: Email | R72: Rompimento de Fibra | U72: 168005 | V72: 168005 | W72: 168005 | X72: MA | Y72: SAO LUIS | AA72: Entre 4h e 8h | AB72: 43.15 | AC72: 36.016666 | AD72: 7.133334 | AE72: 0.333334 | AF72: 0 | AG72: 6.8 | AH72: 6.8 | AI72: 6.533333 | AJ72: 0.266667 | AK72: 0 | AL72: 44865 | AM72: 1163 | AN72: Maior que 15d pós ativação | AO72: SLS/L2L/218787/57 | AP72: MA, PA, PI E AP | AQ72: C.32 - Maranhão | AR72: Wellington Marcio | AT72: S02 | AU72: 2026 | AV72: 1 | AW72: MA CAP | AX72: 1 | AY72: 0 | BT72: MA CAP | BU72: 1 | BV72: 0
A73: 5754085 | B73: 07012026-84747 | C73: Abertura de Reparo SLS/L2L/49019/90- JUIZADO DE TRÂNSITO | D73: Ingrid Alves Lima | E73: Público | F73: 90 | G73: 280007 | H73: 616.59 | I73: TRANSPORTE LAN TO LAN(Wire) | J73: 49495 | K73: FUNDO ESPECIAL DE MODERNIZACAO E REAPARELHAMENTO | L73: 04.408.070/0001-34 | M73: 46029.363 | N73: 46030.628 | O73: PENDENTE VALIDAÇÃO | P73: CMO - Reparo | Q73: Email | R73: Configuração | U73: 168817 | V73: 168331, 168817 | W73: 168331 | X73: MA | Y73: SAO LUIS | AA73: Entre 12h e 24h | AB73: 30.233334 | AC73: 13.883334 | AD73: 16.35 | AE73: 0.866667 | AF73: 0 | AG73: 15.483333 | AH73: 15.483333 | AI73: 14.983333 | AJ73: 0.5 | AK73: 0 | AL73: 44774 | AM73: 1255 | AN73: Maior que 15d pós ativação | AO73: SLS/L2L/49495/90 | AP73: MA, PA, PI E AP | AQ73: C.32 - Maranhão | AR73: Wellington Marcio | AT73: S02 | AU73: 2026 | AV73: 1 | AW73: MA CAP | AX73: 0 | AY73: 0 | BT73: MA CAP | BU73: 0 | BV73: 0
A74: 5734653 | B74: 29122025-95336 | C74: [REQ000142480703] [4289] SAA AG. LENCOIS MARANHENSES | D74: ANA PAULA DA SILVA SANTOS | E74: Operadoras | F74: 940 | G74: 278749 | H74: 475 | I74: TRANSPORTE LAN TO LAN(Wire) | J74: 48887 | K74: BRISANET SERVICOS DE TELECOMUNICACOES LTDA BRISANET SERVICOS DE TELECOMUNICACOES LTDA | L74: 04.601.397/0001-28 | M74: 46020.686 | N74: 46030.635 | O74: ENCAMINHADO AO TÉCNICO | P74: CMO - Reparo | Q74: Portal do Cliente | R74: Configuração | T74: NMA SERVICOS DE TELECOMUNICACOES LTDA | U74: 168343 | V74: 167665, 168343, 168703 | W74: 168703 | X74: MA | Y74: BARREIRINHAS | AA74: Maior que 24h | AB74: 238.53333 | AC74: 189.73333 | AD74: 48.8 | AE74: 0.733333 | AF74: 0 | AG74: 48.066667 | AH74: 48.066667 | AI74: 16.016667 | AJ74: 32.05 | AK74: 0 | AL74: 44441 | AM74: 1579 | AN74: Maior que 15d pós ativação | AO74: BIH/L2L/48887/940 | AP74: MA, PA, PI E AP | AQ74: C.32 - Maranhão | AR74: Wellington Marcio | AT74: S02 | AU74: 2026 | AV74: 1 | AW74: MA INT | AX74: 0 | AY74: 1 | BT74: MA INT | BU74: 0 | BV74: 1
A75: 5755133 | B75: 07012026-81979 | C75: Deposito ASGEP - link inoperante | D75: HOANNA MARIA DA SILVA ALBUQUERQUE | E75: Público | F75: 9 | G75: 280141 | H75: 1200 | I75: TRANSPORTE LAN TO LAN(Wire) | J75: 201809 | K75: TRIBUNAL REGIONAL ELEITORAL DO MARANHAO TRE MA | L75: 05.962.421/0001-17 | M75: 46029.465 | N75: 46030.646 | O75: PENDENTE VALIDAÇÃO | P75: CMO - Reparo | Q75: Portal do Cliente | R75: Rompimento de Fibra | U75: 168427 | V75: 168427 | W75: 168427 | X75: MA | Y75: SAO LUIS | AA75: Entre 4h e 8h | AB75: 28.266667 | AC75: 21.966667 | AD75: 6.3 | AE75: 0.15 | AF75: 0 | AG75: 6.15 | AH75: 6.15 | AI75: 6.116667 | AJ75: 0.033333 | AK75: 0 | AL75: 44357 | AM75: 1672 | AN75: Maior que 15d pós ativação | AO75: SLS/L2L/201809/9 | AP75: MA, PA, PI E AP | AQ75: C.32 - Maranhão | AR75: Wellington Marcio | AT75: S02 | AU75: 2026 | AV75: 1 | AW75: MA CAP | AX75: 1 | AY75: 0 | BT75: MA CAP | BU75: 1 | BV75: 0
A76: 5749847 | B76: 06012026-43250 | C76: MUNICIPIO DE SAO LUIS | INDISPONIBILIDADE | UEB MONSENHOR FREDERICO CHAVES | D76: Stephanie Aparecida Arthur | E76: Público | F76: 180 | G76: 285883 | H76: 364.95 | I76: LINK DE DADOS | J76: 218787 | K76: MUNICIPIO DE SAO LUIS SEMED | L76: 06.307.102/0002-11 | M76: 46028.5 | N76: 46030.718 | O76: PENDENTE VALIDAÇÃO | P76: CMO - Reparo | Q76: Chat | R76: Ajuste de Atenuação | U76: 167995 | V76: 167677, 167995 | W76: 167995 | X76: MA | Y76: SAO LUIS | AA76: Entre 12h e 24h | AB76: 53.166666 | AC76: 38.733333 | AD76: 14.433333 | AE76: 0.05 | AF76: 0 | AG76: 14.383333 | AH76: 14.383333 | AI76: 14.1 | AJ76: 0.283333 | AK76: 0 | AL76: 44868 | AM76: 1160 | AN76: Maior que 15d pós ativação | AO76: SLS/L2L/218787/180 | AP76: MA, PA, PI E AP | AQ76: C.32 - Maranhão | AR76: Wellington Marcio | AT76: S02 | AU76: 2026 | AV76: 1 | AW76: MA CAP | AX76: 0 | AY76: 0 | BT76: MA CAP | BU76: 0 | BV76: 0
A77: 5750347 | B77: 06012026-79543 | C77: ALERTA: CLI | TJMA.SJE.2.VARA.CIVIL.E.CRIMINAL.DE.SAO.JOSE.RIBAMAR.L3VPN.49495.271 - FALHA | D77: Ingrid Alves Lima | E77: Público | F77: 271 | G77: 278103 | H77: 590 | I77: TRANSPORTE LAN TO LAN(Wire) | J77: 49495 | K77: FUNDO ESPECIAL DE MODERNIZACAO E REAPARELHAMENTO | L77: 04.408.070/0001-34 | M77: 46028.626 | N77: 46031.334 | O77: PENDENTE VALIDAÇÃO | P77: CMO - Reparo | Q77: Email | R77: Rompimento de Fibra | U77: 168001 | V77: 167845, 168001 | W77: 168001 | X77: MA | Y77: BARREIRINHAS | AA77: Entre 4h e 8h | AB77: 64.95 | AC77: 58.15 | AD77: 6.8 | AE77: 0.283334 | AF77: 0 | AG77: 6.516666 | AH77: 6.516666 | AI77: 6.266666 | AJ77: 0.25 | AK77: 0 | AL77: 44730 | AM77: 1298 | AN77: Maior que 15d pós ativação | AO77: BIH/L2L/49495/271 | AP77: MA, PA, PI E AP | AQ77: C.32 - Maranhão | AR77: Wellington Marcio | AT77: S02 | AU77: 2026 | AV77: 1 | AW77: MA INT | AX77: 1 | AY77: 0 | BT77: MA INT | BU77: 1 | BV77: 0
A78: 5745867 | B78: 05012026-61844 | C78: Indisponibilidade do link na VT de Santa Izabel do Pará do TRT8 | D78: ANA PAULA DA SILVA SANTOS | E78: Público | F78: 13 | G78: 290927 | H78: 2914.74 | I78: LINK DEDICADO DE INTERNET | J78: 52957 | K78: TRIBUNAL REGIONAL DO TRABALHO DA 8 REGIAO TRIBUNAL REGIONAL DO TRABALHO DA 8 REGIAO | L78: 01.547.343/0001-33 | M78: 46027.374 | N78: 46031.388 | O78: ANALISAR RESPOSTA | P78: CMO - Reparo | Q78: Portal do Cliente | R78: Ajuste de Atenuação | U78: 169013 | V78: 166769, 167057, 167185, 169013, 169333 | W78: 166769, 167057, 167185, 169333 | X78: PA | Y78: SANTA ISABEL DO PARA | AA78: Entre 12h e 24h | AB78: 96.200001 | AC78: 76.366668 | AD78: 19.833333 | AE78: 0.333333 | AF78: 0 | AG78: 19.5 | AH78: 19.5 | AI78: 19 | AJ78: 0.5 | AK78: 0 | AL78: 45244 | AM78: 783 | AN78: Maior que 15d pós ativação | AO78: SIP/IPD/52957/13 | AP78: MA, PA, PI E AP | AQ78: C.28 - Norte | AR78: Wellington Marcio | AT78: S02 | AU78: 2026 | AV78: 1 | AW78: PA INT | AX78: 0 | AY78: 0 | BT78: PA INT | BU78: 0 | BV78: 0
A79: 5756499 | B79: 07012026-84519 | C79: Atendimento para: SECULT - QUILOMBO URBANO - VLAN 4058 SLS0-00216233-00544 | D79: Stephanie Aparecida Arthur | E79: Público | F79: 544 | G79: 297135 | H79: 346.37 | I79: LINK DE DADOS | J79: 216233 | K79: MUNICIPIO DE SAO LUIS SEMIT | L79: 06.307.102/0001-30 | M79: 46029.667 | N79: 46031.462 | O79: PENDENTE VALIDAÇÃO | P79: CMO - Reparo | Q79: E-Care | R79: Rompimento de Fibra | S79: Demais Causas de Rompimento | U79: 168781 | V79: 168781 | W79: 168781 | X79: MA | Y79: SAO LUIS | AA79: Entre 8h e 12h | AB79: 43.000001 | AC79: 33.033334 | AD79: 9.966667 | AE79: 0.15 | AF79: 0 | AG79: 9.816667 | AH79: 9.816667 | AI79: 9.133334 | AJ79: 0.683333 | AK79: 0 | AL79: 45254.69 | AM79: 774 | AN79: Maior que 15d pós ativação | AO79: SLS/L2L/216233/544 | AP79: MA, PA, PI E AP | AQ79: C.32 - Maranhão | AR79: Wellington Marcio | AT79: S02 | AU79: 2026 | AV79: 1 | AW79: MA CAP | AX79: 0 | AY79: 0 | BT79: MA CAP | BU79: 0 | BV79: 0
A80: 5750423 | B80: 06012026-12206 | C80: DOK LTDA | INDISPONIVEL | D80: Julia Ferreira Costa Silva | E80: Corporativo | F80: 1 | G80: 290153 | H80: 1572.45 | I80: LINK DEDICADO DE INTERNET | J80: 217507 | K80: HOSPITAL VETERINARIO DOK LTDA | L80: 27.918.589/0005-91 | M80: 46028.657 | N80: 46031.468 | O80: PENDENTE VALIDAÇÃO | P80: CMO - Reparo | R80: Rompimento de Fibra | U80: 168747 | V80: 167913, 168519, 168727, 168747, 168773 | W80: 168747 | X80: MA | Y80: SAO LUIS | Z80: 524456 | AA80: Maior que 24h | AB80: 67.35 | AC80: 27.333334 | AD80: 40.016666 | AE80: 14.3 | AF80: 13.8 | AG80: 25.716666 | AH80: 39.516666 | AI80: 24.116666 | AJ80: 1.6 | AK80: 0 | AL80: 45045 | AM80: 983 | AN80: Maior que 15d pós ativação | AO80: SLS/IPD/217507/1 | AP80: MA, PA, PI E AP | AQ80: C.32 - Maranhão | AR80: Wellington Marcio | AT80: S02 | AU80: 2026 | AV80: 1 | AW80: MA CAP | AX80: 0 | AY80: 1 | BT80: MA CAP | BU80: 0 | BV80: 1
A81: 5764349 | B81: 08012026-13981 | C81: [REQ000142592648] [2080] SAA AG. SHOPPING DA ILHA | D81: ANA PAULA DA SILVA SANTOS | E81: Operadoras | F81: 672 | G81: 139299 | H81: 400 | I81: LINK DE DADOS | J81: 48887 | K81: BRISANET SERVICOS DE TELECOMUNICACOES LTDA BRISANET SERVICOS DE TELECOMUNICACOES LTDA | L81: 04.601.397/0001-28 | M81: 46030.646 | N81: 46031.47 | O81: PENDENTE VALIDAÇÃO | P81: CMO - Reparo | Q81: Portal do Cliente | R81: Normalizado Sem Intervenção | U81: 169607 | V81: 169415, 169607 | W81: 169415 | X81: MA | Y81: SAO LUIS | AA81: Até 4h | AB81: 19.716666 | AC81: 18.15 | AD81: 1.566666 | AE81: 0.083333 | AF81: 0 | AG81: 1.483333 | AH81: 1.483333 | AI81: 1.033333 | AJ81: 0.45 | AK81: 0 | AL81: 43733 | AM81: 2297 | AN81: Maior que 15d pós ativação | AO81: SLS/L2L/48887/672 | AP81: MA, PA, PI E AP | AQ81: C.32 - Maranhão | AR81: Wellington Marcio | AT81: S02 | AU81: 2026 | AV81: 1 | AW81: MA CAP | AX81: 1 | AY81: 0 | BT81: MA CAP | BU81: 1 | BV81: 0
A82: 5766329 | B82: 08012026-19499 | C82: Atendimento para: CRAS TURU - VLAN 3669 SLS-216233-00042 | D82: Ingrid Alves Lima | E82: Público | F82: 42 | G82: 275271 | H82: 398.82 | I82: LINK DE DADOS | J82: 216233 | K82: MUNICIPIO DE SAO LUIS SEMIT | L82: 06.307.102/0001-30 | M82: 46030.827 | N82: 46031.477 | O82: AGUARDANDO DISPONIBILIDADE TECNICA | P82: CMO - Reparo | Q82: Email | R82: Normalizado Sem Intervenção | U82: 169605 | V82: 169605 | X82: MA | Y82: SAO LUIS | AA82: Até 4h | AB82: 15.533333 | AC82: 11.45 | AD82: 4.083333 | AE82: 0.1 | AF82: 0 | AG82: 3.983333 | AH82: 3.983333 | AI82: 2.866667 | AJ82: 1.116666 | AK82: 0 | AL82: 44873 | AM82: 1157 | AN82: Maior que 15d pós ativação | AO82: SLS/L2L/216233/42 | AP82: MA, PA, PI E AP | AQ82: C.32 - Maranhão | AR82: Wellington Marcio | AT82: S02 | AU82: 2026 | AV82: 1 | AW82: MA CAP | AX82: 1 | AY82: 0 | BT82: MA CAP | BU82: 1 | BV82: 0
A83: 5764291 | B83: 08012026-35277 | C83: ALERTA: CLI | TJMA.SLS.POSTO.HIDRO.PORTUARIO.L3VPN.49495.299 - FALHA | D83: Laura Beatriz de Sibia Santos | E83: Público | F83: 299 | G83: 285731 | H83: 512.08 | I83: TRANSPORTE LAN TO LAN(Wire) | J83: 49495 | K83: FUNDO ESPECIAL DE MODERNIZACAO E REAPARELHAMENTO | L83: 04.408.070/0001-34 | M83: 46030.626 | N83: 46031.515 | O83: PENDENTE VALIDAÇÃO | P83: CMO - Reparo | Q83: Email | R83: Normalizado Sem Intervenção | U83: 169601 | V83: 169403, 169601 | X83: MA | Y83: SAO LUIS | AA83: Entre 4h e 8h | AB83: 21.233334 | AC83: 14.433334 | AD83: 6.8 | AE83: 0.266666 | AF83: 0 | AG83: 6.533334 | AH83: 6.533334 | AI83: 6.3 | AJ83: 0.233334 | AK83: 0 | AL83: 44862 | AM83: 1168 | AN83: Maior que 15d pós ativação | AO83: SLS/L2L/49495/299 | AP83: MA, PA, PI E AP | AQ83: C.32 - Maranhão | AR83: Wellington Marcio | AT83: S02 | AU83: 2026 | AV83: 1 | AW83: MA CAP | AX83: 1 | AY83: 0 | BT83: MA CAP | BU83: 1 | BV83: 0
A84: 5747263 | B84: 05012026-10193 | C84: Falha de conectividade na Promotoria de Justiça da PJECA | D84: Stephanie Aparecida Arthur | E84: Público | F84: 124 | G84: 326469 | H84: 621.57 | I84: LINK DE DADOS | J84: 149307 | K84: ESTADO DO MARANHAO PROCURADORIA GERAL DA JUSTICA PROCURADORIA GERAL DA JUSTICA | L84: 05.483.912/0001-85 | M84: 46027.653 | N84: 46031.531 | O84: PENDENTE VALIDAÇÃO | P84: CMO - Reparo | Q84: E-Care | R84: Rompimento de Fibra | U84: 168777 | V84: 168639, 168777 | W84: 168777 | X84: MA | Y84: SAO LUIS | AA84: Entre 8h e 12h | AB84: 92.949999 | AC84: 83.55 | AD84: 9.399999 | AE84: 1.299999 | AF84: 0 | AG84: 8.1 | AH84: 8.1 | AI84: 7.566667 | AJ84: 0.533333 | AK84: 0 | AL84: 45554 | AM84: 473 | AN84: Maior que 15d pós ativação | AO84: SLS/L2L/149307/124 | AP84: MA, PA, PI E AP | AQ84: C.32 - Maranhão | AR84: Wellington Marcio | AT84: S02 | AU84: 2026 | AV84: 1 | AW84: MA CAP | AX84: 0 | AY84: 0 | BT84: MA CAP | BU84: 0 | BV84: 0
A85: 5756757 | B85: 07012026-27835 | C85: Atendimento para: SUB PREFEITURA - VLAN-4004 SLS-216233-00445 | D85: Julia Ferreira Costa Silva | E85: Público | F85: 445 | G85: 289319 | H85: 398.82 | I85: LINK DE DADOS | J85: 216233 | K85: MUNICIPIO DE SAO LUIS SEMIT | L85: 06.307.102/0001-30 | M85: 46029.717 | N85: 46031.583 | O85: PENDENTE VALIDAÇÃO | P85: CMO - Reparo | Q85: Email | R85: Rompimento de Fibra | U85: 169591 | V85: 168785, 169591 | W85: 169591 | X85: MA | Y85: SAO LUIS | AA85: Entre 12h e 24h | AB85: 44.666667 | AC85: 31.966667 | AD85: 12.7 | AE85: 0.55 | AF85: 0 | AG85: 12.15 | AH85: 12.15 | AI85: 12.033333 | AJ85: 0.116667 | AK85: 0 | AL85: 45014 | AM85: 1015 | AN85: Maior que 15d pós ativação | AO85: SLS/L2L/216233/445 | AP85: MA, PA, PI E AP | AQ85: C.32 - Maranhão | AR85: Wellington Marcio | AT85: S02 | AU85: 2026 | AV85: 1 | AW85: MA CAP | AX85: 0 | AY85: 0 | BT85: MA CAP | BU85: 0 | BV85: 0
A86: 5754593 | B86: 07012026-76845 | C86: Atendimento para: UEB ENS FUND ANTONIO VIEIRA - SLS-216233-00293 | D86: Julia Ferreira Costa Silva | E86: Público | F86: 293 | G86: 286461 | H86: 364.96 | I86: LINK DE DADOS | J86: 218787 | K86: MUNICIPIO DE SAO LUIS SEMED | L86: 06.307.102/0002-11 | M86: 46029.417 | N86: 46031.694 | O86: PENDENTE VALIDAÇÃO | P86: CMO - Reparo | Q86: Email | R86: Ajuste de Atenuação | U86: 168775 | V86: 168517, 168775 | W86: 168775 | X86: MA | Y86: SAO LUIS | AA86: Entre 8h e 12h | AB86: 54.550001 | AC86: 42.816667 | AD86: 11.733334 | AE86: 2.316667 | AF86: 0 | AG86: 9.416667 | AH86: 9.416667 | AI86: 9.35 | AJ86: 0.066667 | AK86: 0 | AL86: 44924 | AM86: 1105 | AN86: Maior que 15d pós ativação | AO86: SLS/L2L/218787/293 | AP86: MA, PA, PI E AP | AQ86: C.32 - Maranhão | AR86: Wellington Marcio | AT86: S02 | AU86: 2026 | AV86: 1 | AW86: MA CAP | AX86: 0 | AY86: 0 | BT86: MA CAP | BU86: 0 | BV86: 0
A87: 5769959 | B87: 10012026-94078 | C87: ALERTA: CLI | SENAI-PA.BLM.ISI#BLM/IPD/203391/16 - FALHA | D87: Ingrid Alves Lima | E87: Público | F87: 16 | G87: 250813 | H87: 2383.33 | I87: LINK DEDICADO DE INTERNET | J87: 203391 | K87: SERVICO NACIONAL DE APRENDIZAGEM INDUSTRIAL SENAI DEPARTAMENTO REGIONAL DO PARA | L87: 03.785.762/0001-39 | M87: 46032.216 | N87: 46032.313 | O87: PENDENTE AGENDAMENTO | P87: CMO - Reparo | Q87: Email | R87: Normalizado Sem Intervenção | U87: 170337 | V87: 170337 | X87: PA | Y87: BELEM | AA87: Até 4h | AB87: 2.316667 | AC87: 0.966667 | AD87: 1.35 | AE87: 1.3 | AF87: 0 | AG87: 0.05 | AH87: 0.05 | AI87: 0 | AJ87: 0.05 | AK87: 0 | AL87: 44624 | AM87: 1408 | AN87: Maior que 15d pós ativação | AO87: BLM/IPD/203391/16 | AP87: MA, PA, PI E AP | AQ87: C.28 - Norte | AR87: Wellington Marcio | AT87: S02 | AU87: 2026 | AV87: 1 | AW87: PA CAP | AX87: 1 | AY87: 0 | BT87: PA CAP | BU87: 1 | BV87: 0
A88: 5769561 | B88: 09012026-74517 | C88: [INDISPONIBILIDADE TELY] [PARCEIRO MOBWIRE] [CLIENTE CARAJAS TERESINA] | D88: Glen Serafim | E88: Operadoras | F88: 17 | G88: 246723 | H88: 450.37 | I88: LINK DE DADOS | J88: 201805 | K88: SITECNET INFORMATICA LTDA TELY | L88: 06.346.446/0001-59 | M88: 46031.764 | N88: 46032.509 | O88: ANALISAR RESPOSTA | P88: CMO - Reparo | Q88: Email | R88: Ajuste de Atenuação | U88: 170299 | V88: 170299 | W88: 170299 | X88: PI | Y88: TERESINA | AA88: Até 4h | AB88: 17.816666 | AC88: 14.95 | AD88: 2.866666 | AE88: 1.233333 | AF88: 0 | AG88: 1.633333 | AH88: 1.633333 | AI88: 1.2 | AJ88: 0.433333 | AK88: 0 | AL88: 44538.722 | AM88: 1493 | AN88: Maior que 15d pós ativação | AO88: TSA/L2L/201805/17 | AP88: MA, PA, PI E AP | AQ88: C.31 - Piaui | AR88: Wellington Marcio | AT88: S02 | AU88: 2026 | AV88: 1 | AW88: PI CAP | AX88: 1 | AY88: 0 | BT88: PI CAP | BU88: 1 | BV88: 0
A89: 5749903 | B89: 06012026-79062 | C89: MUNICIPIO DE SAO LUIS SEMIT | INDISPONIBILIDADE | UEB ENS FUND ELZUILA ABREU | D89: Glen Serafim | E89: Público | F89: 233 | G89: 286307 | H89: 364.96 | I89: LINK DE DADOS | J89: 216233 | K89: MUNICIPIO DE SAO LUIS SEMIT | L89: 06.307.102/0001-30 | M89: 46028.505 | N89: 46032.514 | O89: PENDENTE VALIDAÇÃO | P89: CMO - Reparo | Q89: Chat | R89: Ajuste de Atenuação | U89: 167997 | V89: 167681, 167997 | W89: 167997 | X89: MA | Y89: SAO LUIS | AA89: Entre 8h e 12h | AB89: 96.149999 | AC89: 87.816666 | AD89: 8.333333 | AE89: 0.116667 | AF89: 0 | AG89: 8.216666 | AH89: 8.216666 | AI89: 8.133333 | AJ89: 0.083333 | AK89: 0 | AL89: 44921 | AM89: 1107 | AN89: Maior que 15d pós ativação | AO89: SLS/L2L/218787/233 | AP89: MA, PA, PI E AP | AQ89: C.32 - Maranhão | AR89: Wellington Marcio | AT89: S02 | AU89: 2026 | AV89: 1 | AW89: MA CAP | AX89: 0 | AY89: 0 | BT89: MA CAP | BU89: 0 | BV89: 0
A90: 5756527 | B90: 07012026-66416 | C90: [REQ000142578486] [3566] SAA AG. SÃO JOÃO DOS PATOS | D90: Glen Serafim | E90: Operadoras | F90: 973 | G90: 278815 | H90: 613.8 | I90: TRANSPORTE LAN TO LAN(Wire) | J90: 48887 | K90: BRISANET SERVICOS DE TELECOMUNICACOES LTDA BRISANET SERVICOS DE TELECOMUNICACOES LTDA | L90: 04.601.397/0001-28 | M90: 46029.675 | N90: 46032.533 | O90: PENDENTE VALIDAÇÃO | P90: CMO - Reparo | Q90: Portal do Cliente | R90: Rompimento de Fibra | U90: 168903 | V90: 168903 | W90: 168903 | X90: MA | Y90: SAO JOAO DOS PATOS | AA90: Entre 12h e 24h | AB90: 68.449998 | AC90: 46.583333 | AD90: 21.866665 | AE90: 3.1 | AF90: 0 | AG90: 18.766665 | AH90: 18.766665 | AI90: 17.299999 | AJ90: 1.466666 | AK90: 0 | AL90: 44441 | AM90: 1588 | AN90: Maior que 15d pós ativação | AO90: SSS/L2L/48887/973 | AP90: MA, PA, PI E AP | AQ90: C.32 - Maranhão | AR90: Wellington Marcio | AT90: S02 | AU90: 2026 | AV90: 1 | AW90: MA INT | AX90: 0 | AY90: 0 | BT90: MA INT | BU90: 0 | BV90: 0
A91: 5756761 | B91: 07012026-26444 | C91: MUNICIPIO DE SAO LUIS SEMIT | INDISPONIBILIDADE | SLS/L2L/216233/155 | D91: Glen Serafim | E91: Público | F91: 155 | G91: 285767 | H91: 382.47 | I91: LINK DE DADOS | J91: 216233 | K91: MUNICIPIO DE SAO LUIS SEMIT | L91: 06.307.102/0001-30 | M91: 46029.718 | N91: 46032.538 | O91: PENDENTE VALIDAÇÃO | P91: CMO - Reparo | Q91: Chat | R91: Rompimento de Fibra | U91: 168779 | V91: 168779 | W91: 168779 | X91: MA | Y91: SAO LUIS | AA91: Entre 8h e 12h | AB91: 67.599999 | AC91: 58.8 | AD91: 8.799999 | AE91: 0.083333 | AF91: 0 | AG91: 8.716666 | AH91: 8.716666 | AI91: 8.583333 | AJ91: 0.133333 | AK91: 0 | AL91: 44946 | AM91: 1083 | AN91: Maior que 15d pós ativação | AO91: SLS/L2L/216233/155 | AP91: MA, PA, PI E AP | AQ91: C.32 - Maranhão | AR91: Wellington Marcio | AT91: S02 | AU91: 2026 | AV91: 1 | AW91: MA CAP | AX91: 0 | AY91: 0 | BT91: MA CAP | BU91: 0 | BV91: 0
A92: 5756769 | B92: 07012026-30972 | C92: FUNDO MUNICIPAL DE SAUDE DE SAO LUIS MARANHAO | INDISPONIBILIDADE | SLS/L2L/218791/418 | D92: Glen Serafim | E92: Público | F92: 418 | G92: 289249 | H92: 683.73 | I92: LINK DE DADOS | J92: 218791 | K92: FUNDO MUNICIPAL DE SAUDE DE SAO LUIS MARANHAO | L92: 13.816.886/0001-98 | M92: 46029.72 | N92: 46032.541 | O92: PENDENTE VALIDAÇÃO | P92: CMO - Reparo | Q92: Chat | R92: Rompimento de Fibra | U92: 168783 | V92: 168783 | W92: 168783 | X92: MA | Y92: SAO LUIS | AA92: Entre 4h e 8h | AB92: 67.616667 | AC92: 59.9 | AD92: 7.716667 | AE92: 0.1 | AF92: 0 | AG92: 7.616667 | AH92: 7.616667 | AI92: 7.216667 | AJ92: 0.4 | AK92: 0 | AL92: 44995.704 | AM92: 1034 | AN92: Maior que 15d pós ativação | AO92: SLS/L2L/218791/418 | AP92: MA, PA, PI E AP | AQ92: C.32 - Maranhão | AR92: Wellington Marcio | AT92: S02 | AU92: 2026 | AV92: 1 | AW92: MA CAP | AX92: 1 | AY92: 0 | BT92: MA CAP | BU92: 1 | BV92: 0
A93: 5764757 | B93: 08012026-13015 | C93: IAP COSMETICOS LTDA INDISPONIBILIDADE | SLS/IPD/56181/6 | D93: Glen Serafim | E93: Corporativo | F93: 6 | G93: 301539 | H93: 290 | I93: LINK DEDICADO DE INTERNET | J93: 56181 | K93: IAP COSMETICOS LTDA | L93: 05.346.644/0028-70 | M93: 46030.67 | N93: 46032.576 | O93: PENDENTE VALIDAÇÃO | P93: CMO - Reparo | Q93: Chat | R93: Rompimento de Fibra | U93: 169613 | V93: 169457, 169613, 170287 | W93: 170287 | X93: MA | Y93: SAO LUIS | AA93: Entre 12h e 24h | AB93: 45.666666 | AC93: 32.299999 | AD93: 13.366667 | AE93: 0.483334 | AF93: 0 | AG93: 12.883333 | AH93: 12.883333 | AI93: 11.916666 | AJ93: 0.966667 | AK93: 0 | AL93: 45391.704 | AM93: 638 | AN93: Maior que 15d pós ativação | AO93: SLS/IPD/56181/6 | AP93: MA, PA, PI E AP | AQ93: C.32 - Maranhão | AR93: Wellington Marcio | AT93: S02 | AU93: 2026 | AV93: 1 | AW93: MA CAP | AX93: 0 | AY93: 0 | BT93: MA CAP | BU93: 0 | BV93: 0
A94: 5763101 | B94: 08012026-89670 | C94: FUNDO MUNICIPAL DE SAUDE DE SAO LUIS MARANHAO | INDISPONIBILIDADE | SLS/L2L/218791/225 | D94: Glen Serafim | E94: Público | F94: 225 | G94: 286247 | H94: 368.16 | I94: LINK DE DADOS | J94: 218791 | K94: FUNDO MUNICIPAL DE SAUDE DE SAO LUIS MARANHAO | L94: 13.816.886/0001-98 | M94: 46030.484 | N94: 46032.591 | O94: PENDENTE VALIDAÇÃO | P94: CMO - Reparo | Q94: Chat | R94: Rompimento de Fibra | U94: 169201 | V94: 169201 | W94: 169201 | X94: MA | Y94: SAO LUIS | AA94: Entre 4h e 8h | AB94: 50.516667 | AC94: 44.416667 | AD94: 6.1 | AE94: 0.066667 | AF94: 0 | AG94: 6.033333 | AH94: 6.033333 | AI94: 5.816666 | AJ94: 0.216667 | AK94: 0 | AL94: 44876.623 | AM94: 1153 | AN94: Maior que 15d pós ativação | AO94: SLS/L2L/218791/225 | AP94: MA, PA, PI E AP | AQ94: C.32 - Maranhão | AR94: Wellington Marcio | AT94: S02 | AU94: 2026 | AV94: 1 | AW94: MA CAP | AX94: 1 | AY94: 0 | BT94: MA CAP | BU94: 1 | BV94: 0
A95: 5758451 | B95: 07012026-33927 | C95: Atendimento para: UEB ENS FUND TANCREDO NEVES- Anexo ISEMA - SLS-216233-00296 | D95: Stephanie Aparecida Arthur | E95: Público | F95: 296 | G95: 286471 | H95: 364.96 | I95: LINK DE DADOS | J95: 218787 | K95: MUNICIPIO DE SAO LUIS SEMED | L95: 06.307.102/0002-11 | M95: 46029.994 | N95: 46033.399 | O95: PENDENTE VALIDAÇÃO | P95: CMO - Reparo | Q95: Email | R95: Rompimento de Fibra | U95: 169589 | V95: 168763, 169527, 169589 | W95: 169527 | X95: MA | Y95: SAO LUIS | AA95: Entre 12h e 24h | AB95: 81.616668 | AC95: 63.3 | AD95: 18.316668 | AE95: 0.3 | AF95: 0 | AG95: 18.016668 | AH95: 18.016668 | AI95: 16.833334 | AJ95: 1.183334 | AK95: 0 | AL95: 44922 | AM95: 1107 | AN95: Maior que 15d pós ativação | AO95: SLS/L2L/218787/296 | AP95: MA, PA, PI E AP | AQ95: C.32 - Maranhão | AR95: Wellington Marcio | AT95: S02 | AU95: 2026 | AV95: 1 | AW95: MA CAP | AX95: 0 | AY95: 0 | BT95: MA CAP | BU95: 0 | BV95: 0
A96: 5767245 | B96: 08012026-52119 | C96: Atendimento para: UEB ENS FUND SANTO ANTONIO - SLS-216233-00307 | D96: Stephanie Aparecida Arthur | E96: Público | F96: 307 | G96: 286503 | H96: 364.96 | I96: LINK DE DADOS | J96: 218787 | K96: MUNICIPIO DE SAO LUIS SEMED | L96: 06.307.102/0002-11 | M96: 46030.892 | N96: 46033.406 | O96: PENDENTE VALIDAÇÃO | P96: CMO - Reparo | Q96: Email | R96: Normalizado Sem Intervenção | U96: 169577 | V96: 169577, 169615 | X96: MA | Y96: SAO LUIS | AA96: Entre 8h e 12h | AB96: 60.283334 | AC96: 48.416667 | AD96: 11.866667 | AE96: 2.366667 | AF96: 0 | AG96: 9.5 | AH96: 9.5 | AI96: 8.7 | AJ96: 0.8 | AK96: 0 | AL96: 44933 | AM96: 1097 | AN96: Maior que 15d pós ativação | AO96: SLS/L2L/218787/307 | AP96: MA, PA, PI E AP | AQ96: C.32 - Maranhão | AR96: Wellington Marcio | AT96: S02 | AU96: 2026 | AV96: 1 | AW96: MA CAP | AX96: 0 | AY96: 0 | BT96: MA CAP | BU96: 0 | BV96: 0
A97: 5769029 | B97: 09012026-34497 | C97: ALERTA: CLI | MPMA.BJU.BARAO.DE.GRAJAU.L2L.149307.8 - FALHA | D97: Stephanie Aparecida Arthur | E97: Público | F97: 8 | G97: 279647 | H97: 516.22 | I97: TRANSPORTE LAN TO LAN(Wire) | J97: 149307 | K97: ESTADO DO MARANHAO PROCURADORIA GERAL DA JUSTICA PROCURADORIA GERAL DA JUSTICA | L97: 05.483.912/0001-85 | M97: 46031.542 | N97: 46033.411 | O97: PENDENTE VALIDAÇÃO | P97: CMO - Reparo | Q97: Email | R97: Normalizado Sem Intervenção | T97: G T LOPES & CIA LTDA | U97: 170083 | V97: 170083 | X97: MA | Y97: ARAME | AA97: Até 4h | AB97: 44.816668 | AC97: 40.9 | AD97: 3.916668 | AE97: 0.333334 | AF97: 0 | AG97: 3.583334 | AH97: 3.583334 | AI97: 3.566667 | AJ97: 0.016667 | AK97: 0 | AL97: 44804 | AM97: 1227 | AN97: Maior que 15d pós ativação | AO97: ARM/L2L/149307/8 | AP97: MA, PA, PI E AP | AQ97: C.32 - Maranhão | AR97: Wellington Marcio | AT97: S02 | AU97: 2026 | AV97: 1 | AW97: MA INT | AX97: 1 | AY97: 0 | BT97: MA INT | BU97: 1 | BV97: 0
A98: 5769157 | B98: 09012026-77811 | C98: LACMAR LABORATORIO DE ANALISES CLINICAS DO MARANHAO LTDA | Indisponibilidade | SLS/IPD/204321/7 | D98: Stephanie Aparecida Arthur | E98: Corporativo | F98: 7 | G98: 302279 | H98: 360.5 | I98: LINK DEDICADO DE INTERNET | J98: 204321 | K98: LACMAR LABORATORIO DE ANALISES CLINICAS DO MARANHAO LTDA LACMAR | L98: 20.815.524/0001-48 | M98: 46031.592 | N98: 46033.466 | O98: PENDENTE VALIDAÇÃO | P98: CMO - Reparo | Q98: Chat | R98: Configuração | U98: 170345 | V98: 170125, 170345 | W98: 170345 | X98: MA | Y98: SAO LUIS | AA98: Entre 8h e 12h | AB98: 44.85 | AC98: 32.983333 | AD98: 11.866667 | AE98: 0.15 | AF98: 0 | AG98: 11.716667 | AH98: 11.716667 | AI98: 11.7 | AJ98: 0.016667 | AK98: 0 | AL98: 45425 | AM98: 606 | AN98: Maior que 15d pós ativação | AO98: SLS/IPD/204321/7 | AP98: MA, PA, PI E AP | AQ98: C.32 - Maranhão | AR98: Wellington Marcio | AT98: S02 | AU98: 2026 | AV98: 1 | AW98: MA CAP | AX98: 0 | AY98: 0 | BT98: MA CAP | BU98: 0 | BV98: 0
A99: 5768857 | B99: 09012026-35665 | C99: Abertura de Chamado - EVE260100050939 | D99: ANA PAULA DA SILVA SANTOS | E99: Operadoras | F99: 860 | G99: 326509 | H99: 1050.01 | I99: LINK DE DADOS | J99: 82709 | K99: TIM S A | L99: 02.421.421/0024-08 | M99: 46031.452 | N99: 46033.468 | O99: PENDENTE VALIDAÇÃO | P99: CMO - Reparo | Q99: Email | R99: Rompimento de Fibra | U99: 170005 | V99: 170005 | W99: 170005 | X99: PI | Y99: PICOS | AA99: Entre 4h e 8h | AB99: 48.35 | AC99: 42.033333 | AD99: 6.316667 | AE99: 0.15 | AF99: 0 | AG99: 6.166667 | AH99: 6.166667 | AI99: 6.083334 | AJ99: 0.083333 | AK99: 0 | AL99: 45626 | AM99: 405 | AN99: Maior que 15d pós ativação | AO99: PCZ/L2L/82709/860 | AP99: MA, PA, PI E AP | AQ99: C.31 - Piaui | AR99: Wellington Marcio | AT99: S02 | AU99: 2026 | AV99: 1 | AW99: PI INT | AX99: 1 | AY99: 0 | BT99: PI INT | BU99: 1 | BV99: 0
A100: 5762913 | B100: 08012026-17910 | C100: Atendimento para: Abrigo amar e acolher parque shalon - semcas | D100: Stephanie Aparecida Arthur | E100: Público | F100: 579 | G100: 325841 | H100: 382.47 | I100: LINK DE DADOS | J100: 216233 | K100: MUNICIPIO DE SAO LUIS SEMIT | L100: 06.307.102/0001-30 | M100: 46030.475 | N100: 46033.533 | O100: PENDENTE VALIDAÇÃO | P100: CMO - Reparo | Q100: Email | R100: Rompimento de Fibra | U100: 169597 | V100: 169199, 169597 | W100: 169597 | X100: MA | Y100: SAO LUIS | AA100: Entre 12h e 24h | AB100: 73.333334 | AC100: 58.1 | AD100: 15.233334 | AE100: 0.416667 | AF100: 0 | AG100: 14.816667 | AH100: 14.816667 | AI100: 14.316667 | AJ100: 0.5 | AK100: 0 | AL100: 45561 | AM100: 469 | AN100: Maior que 15d pós ativação | AO100: SLS/L2L/216233/579 | AP100: MA, PA, PI E AP | AQ100: C.32 - Maranhão | AR100: Wellington Marcio | AT100: S02 | AU100: 2026 | AV100: 1 | AW100: MA CAP | AX100: 0 | AY100: 0 | BT100: MA CAP | BU100: 0 | BV100: 0
...

Sheet CONTROLE
A1: 📋 CONTROLE DE CHAMADOS — GESTÃO SEMANAL B2B
A2: Atualização automática via BASE BI | Selecione a semana para filtrar todos os indicadores
B4: SELEÇÃO DE SEMANA | F4: METAS EDITÁVEIS
B5: Semana do Ano: | D5: S16 | F5: B2B Reparo ≤8h (meta ≥): | I5: 0.85
D6: =VALUE(MID(D5,2,LEN(D5)-1)) -> 16 | F6: B2B Outlier >24h (teto ≤): | I6: 0.02
B7: Data Início: | D7: =DATE(2026,1,1)+((D6-1)*7)-WEEKDAY(DATE(2026,1,1),2)+1 -> 46125 | F7: * Edite diretamente as células I5 e I6 para alterar as metas
B8: Data Fim: | D8: =D7+6 -> 46131
B9: Total chamados na semana: | D9: =COUNTIFS('BASE BI'!N:N,">="&D7,'BASE BI'!N:N,"<="&D8+0.99999) -> 106
B11: INDICADORES DA SEMANA SELECIONADA
B12: B2B Reparo ≤8h (Aderência) | E12: B2B Outlier >24h (% casos fora) | H12: Total Chamados Semana | K12: Casos ≤8h (qtd) | N12: Casos >24h (qtd)
B13: =IFERROR(COUNTIFS('BASE BI'!N:N,">="&D7,'BASE BI'!N:N,"<="&D8+0.99999,'BASE BI'!AH:AH,"<="&8)/D9,0) -> 0.39622642 | E13: =IFERROR(COUNTIFS('BASE BI'!N:N,">="&D7,'BASE BI'!N:N,"<="&D8+0.99999,'BASE BI'!AH:AH,">"&24)/D9,0) -> 0.25471698 | H13: =D9 -> 106 | K13: =IFERROR(COUNTIFS('BASE BI'!N:N,">="&D7,'BASE BI'!N:N,"<="&D8+0.99999,'BASE BI'!AH:AH,"<="&8),0) -> 42 | N13: =IFERROR(COUNTIFS('BASE BI'!N:N,">="&D7,'BASE BI'!N:N,"<="&D8+0.99999,'BASE BI'!AH:AH,">"&24),0) -> 27
B14: =IF(D9=0,"SEM DADOS",IF(B13>=I5,"✔ DENTRO DA META","✘ DESVIO: "&TEXT(B13-I5,"0.0%"))) -> ✘ DESVIO: -45% | E14: =IF(D9=0,"SEM DADOS",IF(E13<=I6,"✔ DENTRO DO TETO","✘ ACIMA: +"&TEXT(E13-I6,"0.0%"))) -> ✘ ACIMA: +23%
B16: RESUMO POR CLUSTER / UF — SEMANA SELECIONADA
B17: Cluster / UF | D17: Total | E17: Casos ≤8h | F17: Ader. ≤8h | G17: Meta 85% | H17: Status ≤8h | I17: Casos >24h | J17: % Outlier | K17: Teto 2% | L17: Status >24h
B18: MA CAP (São Luís, Paço, SJR) | D18: =IFERROR(COUNTIFS('BASE BI'!N:N,">="&D7,'BASE BI'!N:N,"<="&D8+0.99999,'BASE BI'!BT:BT,"MA CAP"),0) -> 68 | E18: =IFERROR(COUNTIFS('BASE BI'!N:N,">="&D7,'BASE BI'!N:N,"<="&D8+0.99999,'BASE BI'!BT:BT,"MA CAP",'BASE BI'!AH:AH,"<="&8),0) -> 20 | F18: =IFERROR(E18/D18,0) -> 0.29411765 | G18: =I5 -> 0.85 | H18: =IF(D18=0,"-",IF(F18>=$I$5,"✔ OK","✘ DESVIO")) -> ✘ DESVIO | I18: =IFERROR(COUNTIFS('BASE BI'!N:N,">="&D7,'BASE BI'!N:N,"<="&D8+0.99999,'BASE BI'!BT:BT,"MA CAP",'BASE BI'!AH:AH,">"&24),0) -> 21 | J18: =IFERROR(I18/D18,0) -> 0.30882353 | K18: =I6 -> 0.02 | L18: =IF(D18=0,"-",IF(J18<=$I$6,"✔ OK","✘ DESVIO")) -> ✘ DESVIO
B19: MA INT (demais cidades MA) | D19: =IFERROR(COUNTIFS('BASE BI'!N:N,">="&D7,'BASE BI'!N:N,"<="&D8+0.99999,'BASE BI'!BT:BT,"MA INT"),0) -> 11 | E19: =IFERROR(COUNTIFS('BASE BI'!N:N,">="&D7,'BASE BI'!N:N,"<="&D8+0.99999,'BASE BI'!BT:BT,"MA INT",'BASE BI'!AH:AH,"<="&8),0) -> 6 | F19: =IFERROR(E19/D19,0) -> 0.54545455 | G19: =I5 -> 0.85 | H19: =IF(D19=0,"-",IF(F19>=$I$5,"✔ OK","✘ DESVIO")) -> ✘ DESVIO | I19: =IFERROR(COUNTIFS('BASE BI'!N:N,">="&D7,'BASE BI'!N:N,"<="&D8+0.99999,'BASE BI'!BT:BT,"MA INT",'BASE BI'!AH:AH,">"&24),0) -> 4 | J19: =IFERROR(I19/D19,0) -> 0.36363636 | K19: =I6 -> 0.02 | L19: =IF(D19=0,"-",IF(J19<=$I$6,"✔ OK","✘ DESVIO")) -> ✘ DESVIO
B20: PA CAP (Belém, Ananindeua) | D20: =IFERROR(COUNTIFS('BASE BI'!N:N,">="&D7,'BASE BI'!N:N,"<="&D8+0.99999,'BASE BI'!BT:BT,"PA CAP"),0) -> 6 | E20: =IFERROR(COUNTIFS('BASE BI'!N:N,">="&D7,'BASE BI'!N:N,"<="&D8+0.99999,'BASE BI'!BT:BT,"PA CAP",'BASE BI'!AH:AH,"<="&8),0) -> 5 | F20: =IFERROR(E20/D20,0) -> 0.83333333 | G20: =I5 -> 0.85 | H20: =IF(D20=0,"-",IF(F20>=$I$5,"✔ OK","✘ DESVIO")) -> ✘ DESVIO | I20: =IFERROR(COUNTIFS('BASE BI'!N:N,">="&D7,'BASE BI'!N:N,"<="&D8+0.99999,'BASE BI'!BT:BT,"PA CAP",'BASE BI'!AH:AH,">"&24),0) -> 0 | J20: =IFERROR(I20/D20,0) -> 0 | K20: =I6 -> 0.02 | L20: =IF(D20=0,"-",IF(J20<=$I$6,"✔ OK","✘ DESVIO")) -> ✔ OK
B21: PA INT (demais cidades PA) | D21: =IFERROR(COUNTIFS('BASE BI'!N:N,">="&D7,'BASE BI'!N:N,"<="&D8+0.99999,'BASE BI'!BT:BT,"PA INT"),0) -> 4 | E21: =IFERROR(COUNTIFS('BASE BI'!N:N,">="&D7,'BASE BI'!N:N,"<="&D8+0.99999,'BASE BI'!BT:BT,"PA INT",'BASE BI'!AH:AH,"<="&8),0) -> 1 | F21: =IFERROR(E21/D21,0) -> 0.25 | G21: =I5 -> 0.85 | H21: =IF(D21=0,"-",IF(F21>=$I$5,"✔ OK","✘ DESVIO")) -> ✘ DESVIO | I21: =IFERROR(COUNTIFS('BASE BI'!N:N,">="&D7,'BASE BI'!N:N,"<="&D8+0.99999,'BASE BI'!BT:BT,"PA INT",'BASE BI'!AH:AH,">"&24),0) -> 0 | J21: =IFERROR(I21/D21,0) -> 0 | K21: =I6 -> 0.02 | L21: =IF(D21=0,"-",IF(J21<=$I$6,"✔ OK","✘ DESVIO")) -> ✔ OK
B22: PI | D22: =IFERROR(COUNTIFS('BASE BI'!N:N,">="&D7,'BASE BI'!N:N,"<="&D8+0.99999,'BASE BI'!BT:BT,"PI"),0) -> 0 | E22: =IFERROR(COUNTIFS('BASE BI'!N:N,">="&D7,'BASE BI'!N:N,"<="&D8+0.99999,'BASE BI'!BT:BT,"PI",'BASE BI'!AH:AH,"<="&8),0) -> 0 | F22: =IFERROR(E22/D22,0) -> 0 | G22: =I5 -> 0.85 | H22: =IF(D22=0,"-",IF(F22>=$I$5,"✔ OK","✘ DESVIO")) -> - | I22: =IFERROR(COUNTIFS('BASE BI'!N:N,">="&D7,'BASE BI'!N:N,"<="&D8+0.99999,'BASE BI'!BT:BT,"PI",'BASE BI'!AH:AH,">"&24),0) -> 0 | J22: =IFERROR(I22/D22,0) -> 0 | K22: =I6 -> 0.02 | L22: =IF(D22=0,"-",IF(J22<=$I$6,"✔ OK","✘ DESVIO")) -> -
B23: AM INT | D23: =IFERROR(COUNTIFS('BASE BI'!N:N,">="&D7,'BASE BI'!N:N,"<="&D8+0.99999,'BASE BI'!BT:BT,"AM INT"),0) -> 0 | E23: =IFERROR(COUNTIFS('BASE BI'!N:N,">="&D7,'BASE BI'!N:N,"<="&D8+0.99999,'BASE BI'!BT:BT,"AM INT",'BASE BI'!AH:AH,"<="&8),0) -> 0 | F23: =IFERROR(E23/D23,0) -> 0 | G23: =I5 -> 0.85 | H23: =IF(D23=0,"-",IF(F23>=$I$5,"✔ OK","✘ DESVIO")) -> - | I23: =IFERROR(COUNTIFS('BASE BI'!N:N,">="&D7,'BASE BI'!N:N,"<="&D8+0.99999,'BASE BI'!BT:BT,"AM INT",'BASE BI'!AH:AH,">"&24),0) -> 0 | J23: =IFERROR(I23/D23,0) -> 0 | K23: =I6 -> 0.02 | L23: =IF(D23=0,"-",IF(J23<=$I$6,"✔ OK","✘ DESVIO")) -> -
B24: AP | D24: =IFERROR(COUNTIFS('BASE BI'!N:N,">="&D7,'BASE BI'!N:N,"<="&D8+0.99999,'BASE BI'!BT:BT,"AP"),0) -> 3 | E24: =IFERROR(COUNTIFS('BASE BI'!N:N,">="&D7,'BASE BI'!N:N,"<="&D8+0.99999,'BASE BI'!BT:BT,"AP",'BASE BI'!AH:AH,"<="&8),0) -> 1 | F24: =IFERROR(E24/D24,0) -> 0.33333333 | G24: =I5 -> 0.85 | H24: =IF(D24=0,"-",IF(F24>=$I$5,"✔ OK","✘ DESVIO")) -> ✘ DESVIO | I24: =IFERROR(COUNTIFS('BASE BI'!N:N,">="&D7,'BASE BI'!N:N,"<="&D8+0.99999,'BASE BI'!BT:BT,"AP",'BASE BI'!AH:AH,">"&24),0) -> 0 | J24: =IFERROR(I24/D24,0) -> 0 | K24: =I6 -> 0.02 | L24: =IF(D24=0,"-",IF(J24<=$I$6,"✔ OK","✘ DESVIO")) -> ✔ OK
B25: TOTAL GERAL | D25: =SUM(D18:D24) -> 92 | E25: =SUM(E18:E24) -> 33 | F25: =IFERROR(E25/D25,0) -> 0.35869565 | G25: =I5 -> 0.85 | I25: =SUM(I18:I24) -> 25 | J25: =IFERROR(I25/D25,0) -> 0.27173913 | K25: =I6 -> 0.02

Sheet RELATÓRIO EXECUTIVO
A1: RELATÓRIO EXECUTIVO — TEXTO NARRATIVO A NÍVEL DE DIRETORIA | M1: =CONTROLE!D5&CHAR(10)&TEXT(CONTROLE!D7,"DD/MM")&" a "&TEXT(CONTROLE!D8,"DD/MM") -> S16 13/04 a 19/04
A2: Semana selecionada em CONTROLE | Gerado automaticamente com base nos dados da BASE BI
A4: Total chamados | D4: B2B Reparo ≤8h | G4: Outlier >24h | J4: Localidades c/ desvio
A5: =CONTROLE!D9 -> 106 | D5: =CONTROLE!B13 -> 0.39622642 | G5: =CONTROLE!E13 -> 0.25471698 | J5: =COUNTIF(CONTROLE!H18:H24,"✘ DESVIO") -> 5
A6: ="semana "&CONTROLE!D5 -> semana S16 | D6: ="meta "&TEXT(CONTROLE!I5,"0%")&" | "&TEXT(CONTROLE!B13-CONTROLE!I5,"+0.0%;-0.0%;0.0%")&"pp" -> meta 85% | -45%pp | G6: ="teto "&TEXT(CONTROLE!I6,"0%")&" | "&TEXT(CONTROLE!E13-CONTROLE!I6,"+0.0%;-0.0%;0.0%")&"pp" -> teto 2% | +23%pp | J6: =IF(J5=0,"sem cidades em desvio","cidades impactadas") -> cidades impactadas
A8: ▼ B2B Reparo 8h — Desvio de prazo | 64 casos de 108 (59,26%) | L8: DESVIO CRÍTICO
A9: B2B Reparo 8h – Desvio em 14 localidades representando (64 /108) casos - 59% das perdas de prazo de 8 horas, Sao Luis - MA (45 Casos - 41,67%) devido demais causas de rompimento, Sao Jose De Ribamar - MA (3 Casos - 2,78%) devido demais causas de rompimento, Teresina - PI (3 Casos - 2,78%) devido demais causas configuração, Castanhal - PA (2 Casos - 1,85%) devido demais causas de rompimento, Macapa - AP (2 Casos - 1,85%) devido demais causas de rompimento, Ananindeua - PA (1 Caso - 0,93%) devido demais causas de rompimento, Balsas - MA (1 Caso - 0,93%) devido sem ação, Barra Do Corda - MA (1 Caso - 0,93%) devido demais causas de atenuação, Benevides - PA (1 Caso - 0,93%) devido demais causas de rompimento, Itaporanga - MA (1 Caso - 0,93%) devido demais causas de rompimento, Olinda Nova Do Maranhao - MA (1 Caso - 0,93%) devido demais causas de atenuação, Presidente Dutra - MA (1 Caso - 0,93%) devido demais causas de elétrica, Santa Ines - MA (1 Caso - 0,93%) devido sem ação, Simoes - PI (1 Caso - 0,93%) devido demais causas configuração.
A10: Este texto é gerado automaticamente pela aba RELATÓRIO EXECUTIVO com base nos dados da semana selecionada em CONTROLE. O campo é editável pelo gestor para acrescentar contexto operacional (ex.: obras COP30, condições climáticas, ações de parceiros).
A11: Localidade | C11: UF | D11: Cluster | E11: Casos Fora ≤8h | F11: % do Total | G11: Causa Principal | L11: Parceiro
A12: SAO LUIS | C12: MA | D12: MA CAP | E12: 45 | F12: 0.41666667 | G12: Demais Causas de Rompimento | L12: =IFERROR(INDEX('BASE BI'!T:T,MATCH(A12,'BASE BI'!Y:Y,0)),"—") -> 0
A13: SAO JOSE DE RIBAMAR | C13: MA | D13: MA CAP | E13: 3 | F13: 0.027777778 | G13: Demais Causas de Rompimento | L13: =IFERROR(INDEX('BASE BI'!T:T,MATCH(A13,'BASE BI'!Y:Y,0)),"—") -> NMA SERVICOS DE TELECOMUNICACOES LTDA
A14: TERESINA | C14: PI | D14: PI CAP | E14: 3 | F14: 0.027777778 | G14: Demais Causas Configuração | L14: =IFERROR(INDEX('BASE BI'!T:T,MATCH(A14,'BASE BI'!Y:Y,0)),"—") -> 0
A15: CASTANHAL | C15: PA | D15: PA INT | E15: 2 | F15: 0.018518519 | G15: Demais Causas de Rompimento | L15: =IFERROR(INDEX('BASE BI'!T:T,MATCH(A15,'BASE BI'!Y:Y,0)),"—") -> 0
A16: MACAPA | C16: AP | D16: AP CAP | E16: 2 | F16: 0.018518519 | G16: Demais Causas de Rompimento | L16: =IFERROR(INDEX('BASE BI'!T:T,MATCH(A16,'BASE BI'!Y:Y,0)),"—") -> 0
A17: ANANINDEUA | C17: PA | D17: PA CAP | E17: 1 | F17: 0.0092592593 | G17: Demais Causas de Rompimento | L17: =IFERROR(INDEX('BASE BI'!T:T,MATCH(A17,'BASE BI'!Y:Y,0)),"—") -> 0
A18: BALSAS | C18: MA | D18: MA INT | E18: 1 | F18: 0.0092592593 | G18: Sem Ação | L18: =IFERROR(INDEX('BASE BI'!T:T,MATCH(A18,'BASE BI'!Y:Y,0)),"—") -> 0
A19: BARRA DO CORDA | C19: MA | D19: MA INT | E19: 1 | F19: 0.0092592593 | G19: Demais causas de Atenuação | L19: =IFERROR(INDEX('BASE BI'!T:T,MATCH(A19,'BASE BI'!Y:Y,0)),"—") -> 0
A20: BENEVIDES | C20: PA | D20: PA INT | E20: 1 | F20: 0.0092592593 | G20: Demais Causas de Rompimento | L20: =IFERROR(INDEX('BASE BI'!T:T,MATCH(A20,'BASE BI'!Y:Y,0)),"—") -> 0
A21: ITAPORANGA | C21: MA | D21: MA INT | E21: 1 | F21: 0.0092592593 | G21: Demais Causas de Rompimento | L21: =IFERROR(INDEX('BASE BI'!T:T,MATCH(A21,'BASE BI'!Y:Y,0)),"—") -> —
A22: OLINDA NOVA DO MARANHAO | C22: MA | D22: MA INT | E22: 1 | F22: 0.0092592593 | G22: Demais causas de Atenuação | L22: =IFERROR(INDEX('BASE BI'!T:T,MATCH(A22,'BASE BI'!Y:Y,0)),"—") -> 0
A24: ▲ B2B Outlier >24h — 28 casos de 108 (25,93%) | Teto: 2% | L24: DESVIO CRÍTICO
A25: B2B Outlier >24h – Semana S16 apresentou performance de 25,93% (28/108) devido às causas concentradas nas localidades: Sao Luis - MA (20 Casos - 18,52%) devido demais causas de rompimento, Barra Do Corda - MA (1 Caso - 0,93%) devido demais causas de atenuação, Itaporanga - MA (1 Caso - 0,93%) devido demais causas de rompimento, Olinda Nova Do Maranhao - MA (1 Caso - 0,93%) devido demais causas de atenuação, Presidente Dutra - MA (1 Caso - 0,93%) devido demais causas de elétrica, Santa Ines - MA (1 Caso - 0,93%) devido sem ação, Sao Jose De Ribamar - MA (1 Caso - 0,93%) devido demais causas de rompimento, Simoes - PI (1 Caso - 0,93%) devido demais causas configuração, Teresina - PI (1 Caso - 0,93%) devido demais causas configuração.
A26: Campo editável. O gestor deve incluir contexto executivo adicional como: negociações em andamento com parceiros, planos de contingência, comprometimentos com prazos de normalização e impacto financeiro estimado.
A27: Localidade | C27: UF | D27: Cluster | E27: Casos >24h | F27: % do Total | G27: Causa Principal | L27: Parceiro
A28: SAO LUIS | C28: MA | D28: MA CAP | E28: 20 | F28: 0.18518519 | G28: Demais Causas de Rompimento | L28: =IFERROR(INDEX('BASE BI'!T:T,MATCH(A28,'BASE BI'!Y:Y,0)),"—") -> 0
A29: BARRA DO CORDA | C29: MA | D29: MA INT | E29: 1 | F29: 0.0092592593 | G29: Demais causas de Atenuação | L29: =IFERROR(INDEX('BASE BI'!T:T,MATCH(A29,'BASE BI'!Y:Y,0)),"—") -> 0
A30: ITAPORANGA | C30: MA | D30: MA INT | E30: 1 | F30: 0.0092592593 | G30: Demais Causas de Rompimento | L30: =IFERROR(INDEX('BASE BI'!T:T,MATCH(A30,'BASE BI'!Y:Y,0)),"—") -> —
A31: OLINDA NOVA DO MARANHAO | C31: MA | D31: MA INT | E31: 1 | F31: 0.0092592593 | G31: Demais causas de Atenuação | L31: =IFERROR(INDEX('BASE BI'!T:T,MATCH(A31,'BASE BI'!Y:Y,0)),"—") -> 0
A32: PRESIDENTE DUTRA | C32: MA | D32: MA INT | E32: 1 | F32: 0.0092592593 | G32: Demais causas de Elétrica | L32: =IFERROR(INDEX('BASE BI'!T:T,MATCH(A32,'BASE BI'!Y:Y,0)),"—") -> 0
A33: SANTA INES | C33: MA | D33: MA INT | E33: 1 | F33: 0.0092592593 | G33: Sem Ação | L33: =IFERROR(INDEX('BASE BI'!T:T,MATCH(A33,'BASE BI'!Y:Y,0)),"—") -> ATEX NET TELECOMUNICAÇÕES LTDA
A34: SAO JOSE DE RIBAMAR | C34: MA | D34: MA CAP | E34: 1 | F34: 0.0092592593 | G34: Demais Causas de Rompimento | L34: =IFERROR(INDEX('BASE BI'!T:T,MATCH(A34,'BASE BI'!Y:Y,0)),"—") -> NMA SERVICOS DE TELECOMUNICACOES LTDA
A35: SIMOES
A36: TERESINA | C36: PI | D36: PI CAP | E36: 1 | F36: 0.0092592593 | G36: Demais Causas Configuração

Sheet REINCIDENTES
A1: 🔄 ANÁLISE DE CHAMADOS REINCIDENTES
A2: Referência: Coluna F (numplan/id serviço) + Coluna J (cliente_id) da BASE BI — Período INDEPENDENTE da aba Controle
A4: FILTRO DE PERÍODO
A5: Data Inicial: | B5: 46023 | C5: ← Edite a data inicial (célula B5)
A6: Data Final: | B6: 46139 | C6: ← Edite a data final (célula B6)
A7: Total chamados no período: | D7: =COUNTIFS('BASE BI'!N:N,">="&B5,'BASE BI'!N:N,"<="&B6+0.99999) -> 1188 | E7: Casos >24h: | G7: =COUNTIFS('BASE BI'!N:N,">="&B5,'BASE BI'!N:N,"<="&B6+0.99999,'BASE BI'!AH:AH,">"&24) -> 121 | H7: Casos ≤8h: | J7: =COUNTIFS('BASE BI'!N:N,">="&B5,'BASE BI'!N:N,"<="&B6+0.99999,'BASE BI'!AH:AH,"<="&8) -> 638 | K7: % Outlier >24h: | M7: =IFERROR(G7/D7,0) -> 0.10185185
A8: INDICADORES DE REINCIDÊNCIA NO PERÍODO
A9: ℹ️ Dados calculados sobre todo o banco. Para filtrar por período, ajuste as datas em B5 e B6 — os dados abaixo refletem ocorrências com 2+ chamados no cliente.
A10: RANKING DE CLIENTES REINCIDENTES NO PERÍODO | N10: REINCID. POR UF
A11: Rank | B11: ID Cliente | C11: Cód. Cliente | D11: Nome Cliente | E11: UF | F11: Cidade | G11: Ocorrências | H11: 1ª Abertura | I11: Última Abertura | J11: Causa Mais Freq. | N11: UF | O11: Ocorr.
A12: 1 | B12: 187 | C12: 216233 | D12: MUNICIPIO DE SAO LUIS SEMIT | E12: MA | F12: SAO LUIS | G12: 7 | H12: 19/01/2026 | I12: 07/03/2026 | J12: Demais Causas de Rompimento | N12: MA | O12: 562
A13: 2 | B13: 129 | C13: 218791 | D13: FUNDO MUNICIPAL DE SAUDE DE SAO LUIS MARANHAO | E13: MA | F13: SAO LUIS | G13: 7 | H13: 27/02/2026 | I13: 22/04/2026 | J13: Demais Causas de Rompimento | N13: PI | O13: 73
A14: 3 | B14: 426 | C14: 216233 | D14: MUNICIPIO DE SAO LUIS SEMIT | E14: MA | F14: SAO LUIS | G14: 7 | H14: 16/01/2026 | I14: 19/04/2026 | J14: Sem Ação | N14: PA | O14: 64
A15: 4 | B15: 422 | C15: 216233 | D15: MUNICIPIO DE SAO LUIS SEMIT | E15: MA | F15: SAO LUIS | G15: 7 | H15: 02/01/2026 | I15: 25/03/2026 | J15: Demais Causas de Rompimento | N15: AP | O15: 7
A16: 5 | B16: 11 | C16: 218297 | D16: J FEITOSA SILVA FILHO LOJAS SANTA MARIA | E16: MA | F16: SAO LUIS | G16: 7 | H16: 03/01/2026 | I16: 06/03/2026 | J16: Demais Causas de Rompimento | N16: AM | O16: 4
A17: 6 | B17: 1 | C17: 225005 | D17: CONDOMINIO DO SHOPPING METROPOLE ANANINDEUA CONDOM | E17: PA | F17: ANANINDEUA | G17: 7 | H17: 06/01/2026 | I17: 23/04/2026 | J17: Sem Ação
A18: 7 | B18: 299 | C18: 49495 | D18: FUNDO ESPECIAL DE MODERNIZACAO E REAPARELHAMENTO | E18: MA | F18: SAO LUIS | G18: 6 | H18: 07/01/2026 | I18: 23/04/2026 | J18: Rede Interna
A19: 8 | B19: 300 | C19: 49495 | D19: FUNDO ESPECIAL DE MODERNIZACAO E REAPARELHAMENTO | E19: MA | F19: ESPERANTINOPOLIS | G19: 6 | H19: 16/01/2026 | I19: 16/04/2026 | J19: Reset Equipamento
A20: 9 | B20: 367 | C20: 218787 | D20: MUNICIPIO DE SAO LUIS SEMED | E20: MA | F20: SAO LUIS | G20: 6 | H20: 06/01/2026 | I20: 30/03/2026 | J20: Demais Causas de Rompimento
A21: 10 | B21: 57 | C21: 218787 | D21: MUNICIPIO DE SAO LUIS SEMED | E21: MA | F21: SAO LUIS | G21: 5 | H21: 06/01/2026 | I21: 14/04/2026 | J21: Demais Causas de Rompimento
A22: 11 | B22: 340 | C22: 218787 | D22: MUNICIPIO DE SAO LUIS SEMED | E22: MA | F22: SAO LUIS | G22: 5 | H22: 12/01/2026 | I22: 27/03/2026 | J22: Demais Causas de Rompimento
A23: 12 | B23: 225 | C23: 218791 | D23: FUNDO MUNICIPAL DE SAUDE DE SAO LUIS MARANHAO | E23: MA | F23: SAO LUIS | G23: 5 | H23: 08/01/2026 | I23: 11/04/2026 | J23: Sem Ação
A24: 13 | B24: 1131 | C24: 83605 | D24: TIM S A TIM S A | E24: MA | F24: SAO LUIS | G24: 5 | H24: 01/02/2026 | I24: 23/04/2026 | J24: Demais Causas de Rompimento
A25: 14 | B25: 7 | C25: 219529 | D25: NORTE BRASIL NETWORK TELECOMUNICACOES LTDA NBN TEL | E25: AM | F25: PARINTINS | G25: 4 | H25: 05/02/2026 | I25: 16/04/2026 | J25: Sem Ação
A26: 15 | B26: 147 | C26: 212995 | D26: RAIA DROGASIL S A | E26: PA | F26: BENEVIDES | G26: 4 | H26: 27/02/2026 | I26: 22/04/2026 | J26: Demais Causas de Rompimento
A27: 16 | B27: 51 | C27: 216233 | D27: MUNICIPIO DE SAO LUIS SEMIT | E27: MA | F27: SAO LUIS | G27: 4 | H27: 13/02/2026 | I27: 22/04/2026 | J27: Demais causas de Atenuação
A28: 17 | B28: 16 | C28: 203391 | D28: SERVICO NACIONAL DE APRENDIZAGEM INDUSTRIAL SENAI | E28: PA | F28: BELEM | G28: 4 | H28: 10/01/2026 | I28: 26/04/2026 | J28: Demais causas de Elétrica
... A61: 50 | B61: 185 | C61: 216233 | D61: MUNICIPIO DE SAO LUIS SEMIT | E61: MA | F61: SAO LUIS | G61: 3 | H61: 18/02/2026 | I61: 23/04/2026 | J61: Demais Causas de Rompimento

Sheet EVOLUÇÃO
A1: 📈 EVOLUÇÃO MENSAL — INDICADORES B2B | Gráficos de Barras com Linha de Tendência
A3: MÊS | B3: TOTAL | C3: DENTRO 8H | D3: % ADER 8H | E3: META 8H | F3: OUTLIER >24H | G3: % OUTLIER | H3: TETO 24H
A4: Janeiro | B4: =COUNTIFS('BASE BI'!N:N,">="&DATE(2026,1,1),'BASE BI'!N:N,"<"&DATE(2026,1+1,1)) -> 309 | C4: =COUNTIFS('BASE BI'!N:N,">="&DATE(2026,1,1),'BASE BI'!N:N,"<"&DATE(2026,1+1,1),'BASE BI'!AH:AH,"<="&8) -> 180 | D4: =IFERROR(C4/B4,0) -> 0.58252427 | E4: =CONTROLE!I5 -> 0.85 | F4: =COUNTIFS('BASE BI'!N:N,">="&DATE(2026,1,1),'BASE BI'!N:N,"<"&DATE(2026,1+1,1),'BASE BI'!AH:AH,">"&24) -> 20 | G4: =IFERROR(F4/B4,0) -> 0.064724919 | H4: =CONTROLE!I6 -> 0.02
A5: Fevereiro | B5: =COUNTIFS('BASE BI'!N:N,">="&DATE(2026,2,1),'BASE BI'!N:N,"<"&DATE(2026,2+1,1)) -> 303 | C5: =COUNTIFS('BASE BI'!N:N,">="&DATE(2026,2,1),'BASE BI'!N:N,"<"&DATE(2026,2+1,1),'BASE BI'!AH:AH,"<="&8) -> 181 | D5: =IFERROR(C5/B5,0) -> 0.59735974 | E5: =CONTROLE!I5 -> 0.85 | F5: =COUNTIFS('BASE BI'!N:N,">="&DATE(2026,2,1),'BASE BI'!N:N,"<"&DATE(2026,2+1,1),'BASE BI'!AH:AH,">"&24) -> 17 | G5: =IFERROR(F5/B5,0) -> 0.056105611 | H5: =CONTROLE!I6 -> 0.02
A6: Março | B6: =COUNTIFS('BASE BI'!N:N,">="&DATE(2026,3,1),'BASE BI'!N:N,"<"&DATE(2026,3+1,1)) -> 275 | C6: =COUNTIFS('BASE BI'!N:N,">="&DATE(2026,3,1),'BASE BI'!N:N,"<"&DATE(2026,3+1,1),'BASE BI'!AH:AH,"<="&8) -> 156 | D6: =IFERROR(C6/B6,0) -> 0.56727273 | E6: =CONTROLE!I5 -> 0.85 | F6: =COUNTIFS('BASE BI'!N:N,">="&DATE(2026,3,1),'BASE BI'!N:N,"<"&DATE(2026,3+1,1),'BASE BI'!AH:AH,">"&24) -> 16 | G6: =IFERROR(F6/B6,0) -> 0.058181818 | H6: =CONTROLE!I6 -> 0.02
A7: Abril | B7: =COUNTIFS('BASE BI'!N:N,">="&DATE(2026,4,1),'BASE BI'!N:N,"<"&DATE(2026,4+1,1)) -> 339 | C7: =COUNTIFS('BASE BI'!N:N,">="&DATE(2026,4,1),'BASE BI'!N:N,"<"&DATE(2026,4+1,1),'BASE BI'!AH:AH,"<="&8) -> 142 | D7: =IFERROR(C7/B7,0) -> 0.41887906 | E7: =CONTROLE!I5 -> 0.85 | F7: =COUNTIFS('BASE BI'!N:N,">="&DATE(2026,4,1),'BASE BI'!N:N,"<"&DATE(2026,4+1,1),'BASE BI'!AH:AH,">"&24) -> 72 | G7: =IFERROR(F7/B7,0) -> 0.21238938 | H7: =CONTROLE!I6 -> 0.02
A8: Abril | B8: 303 | C8: 122 | D8: 0.4026 | E8: 0.85 | F8: 69 | G8: 0.2277 | H8: 0.02

Sheet FCA
A1: 📋 FCA — FATO / CAUSA / AÇÃO — TEXTO EXECUTIVO A NÍVEL DE DIRETORIA
A2: =" Referência: "&CONTROLE!D5&" | "&TEXT(CONTROLE!D7,"DD/MM/AAAA")&" a "&TEXT(CONTROLE!D8,"DD/MM/AAAA")&" | Elaborado por: Gerência CMO-Reparo" -> Referência: S16 | 13/04/2026 a 19/04/2026 | Elaborado por: Gerência CMO-Reparo
A4: ● B2B REPARO ≤8H — Meta: ≥85%
A5: FATO | C5: Na semana selecionada, o indicador B2B Reparo ≤8h registrou aderência abaixo da meta corporativa de 85%. Ver dados detalhados na aba RELATÓRIO EXECUTIVO e CONTROLE. Preencha abaixo a análise executiva para o período.
A6: CAUSA | C6: DESCREVA AQUI as principais causas identificadas para o desvio no indicador B2B Reparo ≤8h: Ex: Obras de readequação da postação pela concessionária Equatorial (COP30) em Belém-PA e Ananindeua-PA; Rompimentos de fibra em múltiplas localidades; Demora em tratativas com parceiros terceirizados (Online Telecom, Interling).
A7: AÇÃO | C7: DESCREVA AQUI as ações corretivas e preventivas planejadas: (1) Escalonamento junto à Equatorial para priorização de obras impactantes no SLA; (2) Revisão de SLA com parceiros Online e Interling; (3) Reforço de equipes de campo nas regiões PA CAP e MA CAP; (4) Mapeamento preventivo de redes críticas expostas a rompimentos.
A9: ● B2B OUTLIER >24H — Teto: ≤2% dos chamados
A10: FATO | C10: Na semana selecionada, o indicador B2B Outlier >24h registrou percentual de casos fora do prazo acima do teto de 2%. Ver dados detalhados na aba RELATÓRIO EXECUTIVO e CONTROLE. Preencha abaixo a análise executiva para o período.
A11: CAUSA | C11: DESCREVA AQUI as principais causas dos outliers >24h: Ex: Obras Equatorial/COP30 em Ananindeua-PA (maior concentração); Rompimentos de rede em Belém-PA; Demoras operacionais com parceiro Online em Moju-PA; Atenuações e rompimento em São Luís-MA.
A12: AÇÃO | C12: DESCREVA AQUI as ações corretivas: (1) Criação de sala de situação dedicada às obras COP30; (2) Acompanhamento diário de aging por gestor responsável; (3) Aplicação de penalidades contratuais a parceiros com SLA recorrentemente violado; (4) Apresentação de plano de recuperação à diretoria na semana seguinte.
A14: INDICADORES AUTOMÁTICOS DA SEMANA (referência)
A15: Semana | B15: =CONTROLE!D5 -> S16 | C15: Período | D15: =TEXT(CONTROLE!D7,"DD/MM/AAAA")&" a "&TEXT(CONTROLE!D8,"DD/MM/AAAA") -> 13/04/2026 a 19/04/2026 | E15: Total Chamados | F15: =CONTROLE!D9 -> 106 | G15: B2B ≤8h | H15: =TEXT(CONTROLE!B13,"0.0%")&" (meta 85%)" -> 40% (meta 85%) | I15: B2B Outlier >24h | J15: =TEXT(CONTROLE!E13,"0.0%")&" (teto 2%)" -> 25% (teto 2%)

Sheet DASHBOARD
A1: 🎯 DASHBOARD EXECUTIVO B2B — VISÃO GERAL SEMANAL
A2: =" Semana: "&CONTROLE!D5&" | "&TEXT(CONTROLE!D7,"DD/MM/AAAA")&" a "&TEXT(CONTROLE!D8,"DD/MM/AAAA")&" | Gerente: "&'BASE BI'!AS2 -> Semana: S16 | 13/04/2026 a 19/04/2026 | Gerente:
A4: INDICADORES PRINCIPAIS
A5: B2B Reparo ≤8h | E5: Outlier >24h | I5: Total Chamados | M5: Casos >24h
A6: =CONTROLE!B13 -> 0.39622642 | E6: =CONTROLE!E13 -> 0.25471698 | I6: =CONTROLE!D9 -> 106 | M6: =CONTROLE!N13 -> 27
A7: META: 85% | E7: TETO: 2% | I7: SEMANA | M7: LIMITE: ≤2%
A8: =CONTROLE!B14 -> ✘ DESVIO: -45% | E8: =CONTROLE!E14 -> ✘ ACIMA: +23%
A10: SEMÁFORO CONSOLIDADO POR CLUSTER
A11: Indicador / Meta | C11: MA CAP | E11: MA INT | G11: PA CAP | I11: PA INT | K11: PI | M11: AM INT | O11: AP | Q11: GERAL
A12: Reparo ≤8h (meta ≥85%) | C12: =CONTROLE!F18 -> 0.29411765 | E12: =CONTROLE!F19 -> 0.54545455 | G12: =CONTROLE!F20 -> 0.83333333 | I12: =CONTROLE!F21 -> 0.25 | K12: =CONTROLE!F22 -> 0 | M12: =CONTROLE!F23 -> 0 | O12: =TEXT(CONTROLE!F24,"0%") -> 33% | Q12: =TEXT(CONTROLE!B13,"0.0%") -> 40%
A13: Outlier >24h (teto ≤2%) | C13: =CONTROLE!J18 -> 0.30882353 | E13: =CONTROLE!J19 -> 0.36363636 | G13: =CONTROLE!J20 -> 0 | I13: =CONTROLE!J21 -> 0 | K13: =CONTROLE!J22 -> 0 | M13: =CONTROLE!J23 -> 0 | O13: =TEXT(CONTROLE!J24,"0%") -> 0% | Q13: =TEXT(CONTROLE!E13,"0.0%") -> 25%
A16: TOP CAUSAS RAIZ — ACUMULADO
A17: Causa Raiz | B17: Qtd
A18: Demais Causas de Rompimento | B18: 401
A19: Sem Ação | B19: 214
A20: Conector | B20: 74
A21: Demais causas de Atenuação | B21: 63
A22: Demais Causas Configuração | B22: 63
A23: ARRASTO DE REDE | B23: 54
A24: Demais causas de Elétrica | B24: 17
A25: Rede Interna | B25: 16

Sheet INTEGRAÇÃO
A1: MAPA DE INTEGRAÇÃO — VERIFICAÇÃO AUTOMÁTICA
A2: Esta aba confirma que todos os vínculos estão ativos. Ao atualizar a BASE BI ou trocar a semana em CONTROLE, os dados propagam automaticamente.
A4: Aba | B4: Fonte | C4: Ligação | D4: Células-chave | E4: BASE BI? | F4: Semana? | G4: Verificação ao vivo | H4: Status
A5: BASE BI | B5: Fonte primária | C5: Banco de dados | D5: Colunas A:BV | E5: — | F5: — | G5: =IF(COUNTA('BASE BI'!A:A)>1,"OK — "&(COUNTA('BASE BI'!A:A)-1)&" linhas","Vazio") -> OK — 1534 linhas | H5: =IF(ISNUMBER(SEARCH("OK",G5)),"✔ INTEGRADO","⚠ VERIFICAR") -> ✔ INTEGRADO
A6: CONTROLE | B6: BASE BI | C6: COUNTIFS dinâmico | D6: D7,D8,D9,B13,E13,K13,N13 | E6: SIM | F6: SIM | G6: =IF(CONTROLE!D9>0,"OK — "&CONTROLE!D9&" chamados",IF(COUNTA('BASE BI'!A:A)>1,"OK — base ativa / semana sem dados","Verificar base")) -> OK — 106 chamados | H6: =IF(ISNUMBER(SEARCH("OK",G6)),"✔ INTEGRADO","⚠ VERIFICAR") -> ✔ INTEGRADO
A7: REINCIDENTES | B7: BASE BI+datas B5:B6 | C7: COUNTIFS por período | D7: D7,G7,J7,M7 | E7: SIM | F7: NÃO | G7: =IF(REINCIDENTES!D7>0,"OK — "&REINCIDENTES!D7&" chamados","Verificar") -> OK — 1188 chamados | H7: =IF(ISNUMBER(SEARCH("OK",G7)),"✔ INTEGRADO","⚠ VERIFICAR") -> ✔ INTEGRADO
A8: RELATÓRIO EXEC. | B8: CONTROLE | C8: Referência direta | D8: B5,B6,B7,B8,B9,B10 | E8: SIM | F8: SIM | G8: =IF(CONTROLE!D9>0,"OK — relatório alimentado","OK — relatório zero-safe") -> OK — relatório alimentado | H8: =IF(ISNUMBER(SEARCH("OK",G8)),"✔ INTEGRADO","⚠ VERIFICAR") -> ✔ INTEGRADO
A9: EVOLUÇÃO | B9: BASE BI | C9: COUNTIFS por mês | D9: B4:H7 (cada mês) | E9: SIM | F9: NÃO | G9: OK — 309 em Jan | H9: =IF(ISNUMBER(SEARCH("OK",G9)),"✔ INTEGRADO","⚠ VERIFICAR") -> ✔ INTEGRADO
A10: FCA | B10: CONTROLE | C10: Referência direta | D10: A2, células de indicadores | E10: SIM | F10: SIM | G10: =IF(LEN(FCA!A2)>5,"OK","Verificar") -> OK | H10: =IF(ISNUMBER(SEARCH("OK",G10)),"✔ INTEGRADO","⚠ VERIFICAR") -> ✔ INTEGRADO
A11: DASHBOARD | B11: CONTROLE | C11: Referência direta | D11: A6,E6,I6,M6 | E11: SIM | F11: SIM | G11: =IF(CONTROLE!D9>0,"OK — "&CONTROLE!D9&" na semana","OK — dashboard zero-safe") -> OK — 106 na semana | H11: =IF(ISNUMBER(SEARCH("OK",G11)),"✔ INTEGRADO","⚠ VERIFICAR") -> ✔ INTEGRADO
A13: COMO ATUALIZAR OS DADOS
A14: Atualizar BASE BI → | B14: Adicione/remova linhas na aba BASE BI. CONTROLE, RELATÓRIO EXECUTIVO, EVOLUÇÃO, REINCIDENTES e DASHBOARD recalculam automaticamente via COUNTIFS. Nas novas linhas, preencha as colunas BT (cluster), BU (dentro_8h: TRUE se tempo_b2b ≤ 8) e BV (outlier_24h: TRUE se tempo_b2b > 24).
A15: Trocar Semana → | B15: Altere o valor em CONTROLE!D5 (dropdown S1–S52). CONTROLE, RELATÓRIO EXECUTIVO, FCA e DASHBOARD atualizam instantaneamente. EVOLUÇÃO usa meses e REINCIDENTES usa seu próprio período (B5:B6) — ambos independentes da seleção de semana.
A16: Editar Metas → | B16: Altere CONTROLE!I5 (meta ≤8h, padrão 85%) e CONTROLE!I6 (teto >24h, padrão 2%). Todas as abas que referenciam essas células atualizam automaticamente em cascata.
A17: Relatório Executivo → | B17: O texto automático (fundo colorido) atualiza sozinho. Preencha os campos âmbar semanalmente com o contexto operacional: cidades, causas específicas, obras, parceiros e ações corretivas.
